[
  {
    "theme": "AMERICAN GOVERNMENT",
    "section": "Principles of American Democracy",
    "question": "What is the supreme law of the land?",
    "questionNumber": 1,
    "expectedAnswers": 1,
    "answers": {
      "_type": "text",
      "choices": [
        "the Constitution"
      ]
    }
  },
  {
    "theme": "AMERICAN GOVERNMENT",
    "section": "Principles of American Democracy",
    "question": "What does the Constitution do?",
    "questionNumber": 2,
    "expectedAnswers": 1,
    "answers": {
      "_type": "text",
      "choices": [
        "sets up the government",
        "defines the government",
        "protects basic rights of Americans"
      ]
    }
  },
  {
    "theme": "AMERICAN GOVERNMENT",
    "section": "Principles of American Democracy",
    "question": "The idea of self-government is in the first three words of the Constitution. What are these words?",
    "questionNumber": 3,
    "expectedAnswers": 1,
    "answers": {
      "_type": "text",
      "choices": [
        "We the People"
      ]
    }
  },
  {
    "theme": "AMERICAN GOVERNMENT",
    "section": "Principles of American Democracy",
    "question": "What is an amendment?",
    "questionNumber": 4,
    "expectedAnswers": 1,
    "answers": {
      "_type": "text",
      "choices": [
        "a change (to the Constitution)",
        "an addition (to the Constitution)"
      ]
    }
  },
  {
    "theme": "AMERICAN GOVERNMENT",
    "section": "Principles of American Democracy",
    "question": "What do we call the first ten amendments to the Constitution?",
    "questionNumber": 5,
    "expectedAnswers": 1,
    "answers": {
      "_type": "text",
      "choices": [
        "the Bill of Rights"
      ]
    }
  },
  {
    "theme": "AMERICAN GOVERNMENT",
    "section": "Principles of American Democracy",
    "question": "What is one right or freedom from the First Amendment?*",
    "questionNumber": 6,
    "expectedAnswers": 1,
    "answers": {
      "_type": "text",
      "choices": [
        "speech",
        "religion",
        "assembly",
        "press",
        "petition the government"
      ]
    }
  },
  {
    "theme": "AMERICAN GOVERNMENT",
    "section": "Principles of American Democracy",
    "question": "How many amendments does the Constitution have?",
    "questionNumber": 7,
    "expectedAnswers": 1,
    "answers": {
      "_type": "text",
      "choices": [
        "twenty-seven (27)"
      ]
    }
  },
  {
    "theme": "AMERICAN GOVERNMENT",
    "section": "Principles of American Democracy",
    "question": "What did the Declaration of Independence do?",
    "questionNumber": 8,
    "expectedAnswers": 1,
    "answers": {
      "_type": "text",
      "choices": [
        "announced our independence (from Great Britain)",
        "declared our independence (from Great Britain)",
        "said that the United States is free (from Great Britain)"
      ]
    }
  },
  {
    "theme": "AMERICAN GOVERNMENT",
    "section": "Principles of American Democracy",
    "question": "What are two rights in the Declaration of Independence?",
    "questionNumber": 9,
    "expectedAnswers": 2,
    "answers": {
      "_type": "text",
      "choices": [
        "life",
        "liberty",
        "pursuit of happiness"
      ]
    }
  },
  {
    "theme": "AMERICAN GOVERNMENT",
    "section": "Principles of American Democracy",
    "question": "What is freedom of religion?",
    "questionNumber": 10,
    "expectedAnswers": 1,
    "answers": {
      "_type": "text",
      "choices": [
        "You can practice any religion, or not practice a religion."
      ]
    }
  },
  {
    "theme": "AMERICAN GOVERNMENT",
    "section": "Principles of American Democracy",
    "question": "What is the economic system in the United States?*",
    "questionNumber": 11,
    "expectedAnswers": 1,
    "answers": {
      "_type": "text",
      "choices": [
        "capitalist economy",
        "market economy"
      ]
    }
  },
  {
    "theme": "AMERICAN GOVERNMENT",
    "section": "Principles of American Democracy",
    "question": "What is the \"rule of law\"?",
    "questionNumber": 12,
    "expectedAnswers": 1,
    "answers": {
      "_type": "text",
      "choices": [
        "Everyone must follow the law.",
        "Leaders must obey the law.",
        "Government must obey the law.",
        "No one is above the law."
      ]
    }
  },
  {
    "theme": "AMERICAN GOVERNMENT",
    "section": "System of Government",
    "question": "Name one branch or part of the government.*",
    "questionNumber": 13,
    "expectedAnswers": 1,
    "answers": {
      "_type": "text",
      "choices": [
        "Congress",
        "legislative",
        "President",
        "executive",
        "the courts",
        "judicial"
      ]
    }
  },
  {
    "theme": "AMERICAN GOVERNMENT",
    "section": "System of Government",
    "question": "What stops one branch of government from becoming too powerful?",
    "questionNumber": 14,
    "expectedAnswers": 1,
    "answers": {
      "_type": "text",
      "choices": [
        "checks and balances",
        "separation of powers"
      ]
    }
  },
  {
    "theme": "AMERICAN GOVERNMENT",
    "section": "System of Government",
    "question": "Who is in charge of the executive branch?",
    "questionNumber": 15,
    "expectedAnswers": 1,
    "answers": {
      "_type": "text",
      "choices": [
        "the President"
      ]
    }
  },
  {
    "theme": "AMERICAN GOVERNMENT",
    "section": "System of Government",
    "question": "Who makes federal laws?",
    "questionNumber": 16,
    "expectedAnswers": 1,
    "answers": {
      "_type": "text",
      "choices": [
        "Congress",
        "Senate and House (of Representatives)",
        "(U.S. or national) legislature"
      ]
    }
  },
  {
    "theme": "AMERICAN GOVERNMENT",
    "section": "System of Government",
    "question": "What are the two parts of the U.S. Congress?*",
    "questionNumber": 17,
    "expectedAnswers": 1,
    "answers": {
      "_type": "text",
      "choices": [
        "the Senate and House (of Representatives)"
      ]
    }
  },
  {
    "theme": "AMERICAN GOVERNMENT",
    "section": "System of Government",
    "question": "How many U.S. Senators are there?",
    "questionNumber": 18,
    "expectedAnswers": 1,
    "answers": {
      "_type": "text",
      "choices": [
        "one hundred (100)"
      ]
    }
  },
  {
    "theme": "AMERICAN GOVERNMENT",
    "section": "System of Government",
    "question": "We elect a U.S. Senator for how many years?",
    "questionNumber": 19,
    "expectedAnswers": 1,
    "answers": {
      "_type": "text",
      "choices": [
        "six (6)"
      ]
    }
  },
  {
    "theme": "AMERICAN GOVERNMENT",
    "section": "System of Government",
    "question": "Who is one of your state's U.S. Senators now?*",
    "questionNumber": 20,
    "expectedAnswers": 1,
    "answers": {
      "_type": "senator",
      "choices": [
        {
          "senator": "Angela D. Alsobrooks",
          "state": "MD"
        },
        {
          "senator": "Tammy Baldwin",
          "state": "WI"
        },
        {
          "senator": "Jim Banks",
          "state": "IN"
        },
        {
          "senator": "John Barrasso",
          "state": "WY"
        },
        {
          "senator": "Michael F. Bennet",
          "state": "CO"
        },
        {
          "senator": "Marsha Blackburn",
          "state": "TN"
        },
        {
          "senator": "Richard Blumenthal",
          "state": "CT"
        },
        {
          "senator": "Lisa Blunt Rochester",
          "state": "DE"
        },
        {
          "senator": "Cory A. Booker",
          "state": "NJ"
        },
        {
          "senator": "John Boozman",
          "state": "AR"
        },
        {
          "senator": "Katie Boyd Britt",
          "state": "AL"
        },
        {
          "senator": "Ted Budd",
          "state": "NC"
        },
        {
          "senator": "Maria Cantwell",
          "state": "WA"
        },
        {
          "senator": "Shelley Moore Capito",
          "state": "WV"
        },
        {
          "senator": "Bill Cassidy",
          "state": "LA"
        },
        {
          "senator": "Susan M. Collins",
          "state": "ME"
        },
        {
          "senator": "Christopher A. Coons",
          "state": "DE"
        },
        {
          "senator": "John Cornyn",
          "state": "TX"
        },
        {
          "senator": "Catherine Cortez Masto",
          "state": "NV"
        },
        {
          "senator": "Tom Cotton",
          "state": "AR"
        },
        {
          "senator": "Kevin Cramer",
          "state": "ND"
        },
        {
          "senator": "Mike Crapo",
          "state": "ID"
        },
        {
          "senator": "Ted Cruz",
          "state": "TX"
        },
        {
          "senator": "John R. Curtis",
          "state": "UT"
        },
        {
          "senator": "Steve Daines",
          "state": "MT"
        },
        {
          "senator": "Tammy Duckworth",
          "state": "IL"
        },
        {
          "senator": "Richard J. Durbin",
          "state": "IL"
        },
        {
          "senator": "Joni Ernst",
          "state": "IA"
        },
        {
          "senator": "John Fetterman",
          "state": "PA"
        },
        {
          "senator": "Deb Fischer",
          "state": "NE"
        },
        {
          "senator": "Ruben Gallego",
          "state": "AZ"
        },
        {
          "senator": "Kirsten E. Gillibrand",
          "state": "NY"
        },
        {
          "senator": "Lindsey Graham",
          "state": "SC"
        },
        {
          "senator": "Chuck Grassley",
          "state": "IA"
        },
        {
          "senator": "Bill Hagerty",
          "state": "TN"
        },
        {
          "senator": "Margaret Wood Hassan",
          "state": "NH"
        },
        {
          "senator": "Josh Hawley",
          "state": "MO"
        },
        {
          "senator": "Martin Heinrich",
          "state": "NM"
        },
        {
          "senator": "John W. Hickenlooper",
          "state": "CO"
        },
        {
          "senator": "Mazie K. Hirono",
          "state": "HI"
        },
        {
          "senator": "John Hoeven",
          "state": "ND"
        },
        {
          "senator": "Jon Husted",
          "state": "OH"
        },
        {
          "senator": "Cindy Hyde-Smith",
          "state": "MS"
        },
        {
          "senator": "Ron Johnson",
          "state": "WI"
        },
        {
          "senator": "James C. Justice",
          "state": "WV"
        },
        {
          "senator": "Tim Kaine",
          "state": "VA"
        },
        {
          "senator": "Mark Kelly",
          "state": "AZ"
        },
        {
          "senator": "John Kennedy",
          "state": "LA"
        },
        {
          "senator": "Andy Kim",
          "state": "NJ"
        },
        {
          "senator": "Angus S., Jr. King",
          "state": "ME"
        },
        {
          "senator": "Amy Klobuchar",
          "state": "MN"
        },
        {
          "senator": "James Lankford",
          "state": "OK"
        },
        {
          "senator": "Mike Lee",
          "state": "UT"
        },
        {
          "senator": "Ben Ray Luján",
          "state": "NM"
        },
        {
          "senator": "Cynthia M. Lummis",
          "state": "WY"
        },
        {
          "senator": "Edward J. Markey",
          "state": "MA"
        },
        {
          "senator": "Roger Marshall",
          "state": "KS"
        },
        {
          "senator": "Mitch McConnell",
          "state": "KY"
        },
        {
          "senator": "David McCormick",
          "state": "PA"
        },
        {
          "senator": "Jeff Merkley",
          "state": "OR"
        },
        {
          "senator": "Ashley Moody",
          "state": "FL"
        },
        {
          "senator": "Jerry Moran",
          "state": "KS"
        },
        {
          "senator": "Bernie Moreno",
          "state": "OH"
        },
        {
          "senator": "Markwayne Mullin",
          "state": "OK"
        },
        {
          "senator": "Lisa Murkowski",
          "state": "AK"
        },
        {
          "senator": "Christopher Murphy",
          "state": "CT"
        },
        {
          "senator": "Patty Murray",
          "state": "WA"
        },
        {
          "senator": "Jon Ossoff",
          "state": "GA"
        },
        {
          "senator": "Alex Padilla",
          "state": "CA"
        },
        {
          "senator": "Rand Paul",
          "state": "KY"
        },
        {
          "senator": "Gary C. Peters",
          "state": "MI"
        },
        {
          "senator": "Jack Reed",
          "state": "RI"
        },
        {
          "senator": "Pete Ricketts",
          "state": "NE"
        },
        {
          "senator": "James E. Risch",
          "state": "ID"
        },
        {
          "senator": "Jacky Rosen",
          "state": "NV"
        },
        {
          "senator": "Mike Rounds",
          "state": "SD"
        },
        {
          "senator": "Bernard Sanders",
          "state": "VT"
        },
        {
          "senator": "Brian Schatz",
          "state": "HI"
        },
        {
          "senator": "Adam B. Schiff",
          "state": "CA"
        },
        {
          "senator": "Eric Schmitt",
          "state": "MO"
        },
        {
          "senator": "Charles E. Schumer",
          "state": "NY"
        },
        {
          "senator": "Rick Scott",
          "state": "FL"
        },
        {
          "senator": "Tim Scott",
          "state": "SC"
        },
        {
          "senator": "Jeanne Shaheen",
          "state": "NH"
        },
        {
          "senator": "Tim Sheehy",
          "state": "MT"
        },
        {
          "senator": "Elissa Slotkin",
          "state": "MI"
        },
        {
          "senator": "Tina Smith",
          "state": "MN"
        },
        {
          "senator": "Dan Sullivan",
          "state": "AK"
        },
        {
          "senator": "John Thune",
          "state": "SD"
        },
        {
          "senator": "Thom Tillis",
          "state": "NC"
        },
        {
          "senator": "Tommy Tuberville",
          "state": "AL"
        },
        {
          "senator": "Chris Van Hollen",
          "state": "MD"
        },
        {
          "senator": "Mark R. Warner",
          "state": "VA"
        },
        {
          "senator": "Raphael G. Warnock",
          "state": "GA"
        },
        {
          "senator": "Elizabeth Warren",
          "state": "MA"
        },
        {
          "senator": "Peter Welch",
          "state": "VT"
        },
        {
          "senator": "Sheldon Whitehouse",
          "state": "RI"
        },
        {
          "senator": "Roger F. Wicker",
          "state": "MS"
        },
        {
          "senator": "Ron Wyden",
          "state": "OR"
        },
        {
          "senator": "Todd Young",
          "state": "IN"
        }
      ]
    }
  },
  {
    "theme": "AMERICAN GOVERNMENT",
    "section": "System of Government",
    "question": "The House of Representatives has how many voting members?",
    "questionNumber": 21,
    "expectedAnswers": 1,
    "answers": {
      "_type": "text",
      "choices": [
        "four hundred thirty-five (435)"
      ]
    }
  },
  {
    "theme": "AMERICAN GOVERNMENT",
    "section": "System of Government",
    "question": "We elect a U.S. Representative for how many years?",
    "questionNumber": 22,
    "expectedAnswers": 1,
    "answers": {
      "_type": "text",
      "choices": [
        "two (2)"
      ]
    }
  },
  {
    "theme": "AMERICAN GOVERNMENT",
    "section": "System of Government",
    "question": "Name your U.S. Representative.",
    "questionNumber": 23,
    "expectedAnswers": 1,
    "answers": {
      "_type": "representative",
      "choices": [
        {
          "representative": "Moore, Barry",
          "state": "AL"
        },
        {
          "representative": "Figures, Shomari",
          "state": "AL"
        },
        {
          "representative": "Rogers, Mike",
          "state": "AL"
        },
        {
          "representative": "Aderholt, Robert",
          "state": "AL"
        },
        {
          "representative": "Strong, Dale",
          "state": "AL"
        },
        {
          "representative": "Palmer, Gary",
          "state": "AL"
        },
        {
          "representative": "Sewell, Terri",
          "state": "AL"
        },
        {
          "representative": "Begich, Nicholas",
          "state": "AK"
        },
        {
          "representative": "Radewagen, Aumua Amata",
          "state": "AS"
        },
        {
          "representative": "Schweikert, David",
          "state": "AZ"
        },
        {
          "representative": "Crane, Elijah",
          "state": "AZ"
        },
        {
          "representative": "Ansari, Yassamin",
          "state": "AZ"
        },
        {
          "representative": "Stanton, Greg",
          "state": "AZ"
        },
        {
          "representative": "Biggs, Andy",
          "state": "AZ"
        },
        {
          "representative": "Ciscomani, Juan",
          "state": "AZ"
        },
        {
          "representative": "Grijalva, Raúl M.- Vacancy",
          "state": "AZ"
        },
        {
          "representative": "Hamadeh, Abraham",
          "state": "AZ"
        },
        {
          "representative": "Gosar, Paul",
          "state": "AZ"
        },
        {
          "representative": "Crawford, Eric",
          "state": "AR"
        },
        {
          "representative": "Hill, J.",
          "state": "AR"
        },
        {
          "representative": "Womack, Steve",
          "state": "AR"
        },
        {
          "representative": "Westerman, Bruce",
          "state": "AR"
        },
        {
          "representative": "LaMalfa, Doug",
          "state": "CA"
        },
        {
          "representative": "Huffman, Jared",
          "state": "CA"
        },
        {
          "representative": "Kiley, Kevin",
          "state": "CA"
        },
        {
          "representative": "Thompson, Mike",
          "state": "CA"
        },
        {
          "representative": "McClintock, Tom",
          "state": "CA"
        },
        {
          "representative": "Bera, Ami",
          "state": "CA"
        },
        {
          "representative": "Matsui, Doris",
          "state": "CA"
        },
        {
          "representative": "Garamendi, John",
          "state": "CA"
        },
        {
          "representative": "Harder, Josh",
          "state": "CA"
        },
        {
          "representative": "DeSaulnier, Mark",
          "state": "CA"
        },
        {
          "representative": "Pelosi, Nancy",
          "state": "CA"
        },
        {
          "representative": "Simon, Lateefah",
          "state": "CA"
        },
        {
          "representative": "Gray, Adam",
          "state": "CA"
        },
        {
          "representative": "Swalwell, Eric",
          "state": "CA"
        },
        {
          "representative": "Mullin, Kevin",
          "state": "CA"
        },
        {
          "representative": "Liccardo, Sam",
          "state": "CA"
        },
        {
          "representative": "Khanna, Ro",
          "state": "CA"
        },
        {
          "representative": "Lofgren, Zoe",
          "state": "CA"
        },
        {
          "representative": "Panetta, Jimmy",
          "state": "CA"
        },
        {
          "representative": "Fong, Vince",
          "state": "CA"
        },
        {
          "representative": "Costa, Jim",
          "state": "CA"
        },
        {
          "representative": "Valadao, David",
          "state": "CA"
        },
        {
          "representative": "Obernolte, Jay",
          "state": "CA"
        },
        {
          "representative": "Carbajal, Salud",
          "state": "CA"
        },
        {
          "representative": "Ruiz, Raul",
          "state": "CA"
        },
        {
          "representative": "Brownley, Julia",
          "state": "CA"
        },
        {
          "representative": "Whitesides, George",
          "state": "CA"
        },
        {
          "representative": "Chu, Judy",
          "state": "CA"
        },
        {
          "representative": "Rivas, Luz",
          "state": "CA"
        },
        {
          "representative": "Friedman, Laura",
          "state": "CA"
        },
        {
          "representative": "Cisneros, Gilbert",
          "state": "CA"
        },
        {
          "representative": "Sherman, Brad",
          "state": "CA"
        },
        {
          "representative": "Aguilar, Pete",
          "state": "CA"
        },
        {
          "representative": "Gomez, Jimmy",
          "state": "CA"
        },
        {
          "representative": "Torres, Norma",
          "state": "CA"
        },
        {
          "representative": "Lieu, Ted",
          "state": "CA"
        },
        {
          "representative": "Kamlager-Dove, Sydney",
          "state": "CA"
        },
        {
          "representative": "Sanchez, Linda",
          "state": "CA"
        },
        {
          "representative": "Takano, Mark",
          "state": "CA"
        },
        {
          "representative": "Kim, Young",
          "state": "CA"
        },
        {
          "representative": "Calvert, Ken",
          "state": "CA"
        },
        {
          "representative": "Garcia, Robert",
          "state": "CA"
        },
        {
          "representative": "Waters, Maxine",
          "state": "CA"
        },
        {
          "representative": "Barragan, Nanette",
          "state": "CA"
        },
        {
          "representative": "Tran, Derek",
          "state": "CA"
        },
        {
          "representative": "Correa, J.",
          "state": "CA"
        },
        {
          "representative": "Min, Dave",
          "state": "CA"
        },
        {
          "representative": "Issa, Darrell",
          "state": "CA"
        },
        {
          "representative": "Levin, Mike",
          "state": "CA"
        },
        {
          "representative": "Peters, Scott",
          "state": "CA"
        },
        {
          "representative": "Jacobs, Sara",
          "state": "CA"
        },
        {
          "representative": "Vargas, Juan",
          "state": "CA"
        },
        {
          "representative": "DeGette, Diana",
          "state": "CO"
        },
        {
          "representative": "Neguse, Joe",
          "state": "CO"
        },
        {
          "representative": "Hurd, Jeff",
          "state": "CO"
        },
        {
          "representative": "Boebert, Lauren",
          "state": "CO"
        },
        {
          "representative": "Crank, Jeff",
          "state": "CO"
        },
        {
          "representative": "Crow, Jason",
          "state": "CO"
        },
        {
          "representative": "Pettersen, Brittany",
          "state": "CO"
        },
        {
          "representative": "Evans, Gabe",
          "state": "CO"
        },
        {
          "representative": "Larson, John",
          "state": "CT"
        },
        {
          "representative": "Courtney, Joe",
          "state": "CT"
        },
        {
          "representative": "DeLauro, Rosa",
          "state": "CT"
        },
        {
          "representative": "Himes, James",
          "state": "CT"
        },
        {
          "representative": "Hayes, Jahana",
          "state": "CT"
        },
        {
          "representative": "McBride, Sarah",
          "state": "DE"
        },
        {
          "representative": "Norton, Eleanor",
          "state": "DC"
        },
        {
          "representative": "Patronis, Jimmy",
          "state": "FL"
        },
        {
          "representative": "Dunn, Neal",
          "state": "FL"
        },
        {
          "representative": "Cammack, Kat",
          "state": "FL"
        },
        {
          "representative": "Bean, Aaron",
          "state": "FL"
        },
        {
          "representative": "Rutherford, John",
          "state": "FL"
        },
        {
          "representative": "Fine, Randy",
          "state": "FL"
        },
        {
          "representative": "Mills, Cory",
          "state": "FL"
        },
        {
          "representative": "Haridopolos, Mike",
          "state": "FL"
        },
        {
          "representative": "Soto, Darren",
          "state": "FL"
        },
        {
          "representative": "Frost, Maxwell",
          "state": "FL"
        },
        {
          "representative": "Webster, Daniel",
          "state": "FL"
        },
        {
          "representative": "Bilirakis, Gus",
          "state": "FL"
        },
        {
          "representative": "Luna, Anna Paulina",
          "state": "FL"
        },
        {
          "representative": "Castor, Kathy",
          "state": "FL"
        },
        {
          "representative": "Lee, Laurel",
          "state": "FL"
        },
        {
          "representative": "Buchanan, Vern",
          "state": "FL"
        },
        {
          "representative": "Steube, W.",
          "state": "FL"
        },
        {
          "representative": "Franklin, Scott",
          "state": "FL"
        },
        {
          "representative": "Donalds, Byron",
          "state": "FL"
        },
        {
          "representative": "Cherfilus-McCormick, Sheila",
          "state": "FL"
        },
        {
          "representative": "Mast, Brian",
          "state": "FL"
        },
        {
          "representative": "Frankel, Lois",
          "state": "FL"
        },
        {
          "representative": "Moskowitz, Jared",
          "state": "FL"
        },
        {
          "representative": "Wilson, Frederica",
          "state": "FL"
        },
        {
          "representative": "Wasserman Schultz, Debbie",
          "state": "FL"
        },
        {
          "representative": "Diaz-Balart, Mario",
          "state": "FL"
        },
        {
          "representative": "Salazar, Maria",
          "state": "FL"
        },
        {
          "representative": "Gimenez, Carlos",
          "state": "FL"
        },
        {
          "representative": "Carter, Earl",
          "state": "GA"
        },
        {
          "representative": "Bishop, Sanford",
          "state": "GA"
        },
        {
          "representative": "Jack, Brian",
          "state": "GA"
        },
        {
          "representative": "Johnson, Henry",
          "state": "GA"
        },
        {
          "representative": "Williams, Nikema",
          "state": "GA"
        },
        {
          "representative": "McBath, Lucy",
          "state": "GA"
        },
        {
          "representative": "McCormick, Richard",
          "state": "GA"
        },
        {
          "representative": "Scott, Austin",
          "state": "GA"
        },
        {
          "representative": "Clyde, Andrew",
          "state": "GA"
        },
        {
          "representative": "Collins, Mike",
          "state": "GA"
        },
        {
          "representative": "Loudermilk, Barry",
          "state": "GA"
        },
        {
          "representative": "Allen, Rick",
          "state": "GA"
        },
        {
          "representative": "Scott, David",
          "state": "GA"
        },
        {
          "representative": "Greene, Marjorie",
          "state": "GA"
        },
        {
          "representative": "Moylan, James",
          "state": "GU"
        },
        {
          "representative": "Case, Ed",
          "state": "HI"
        },
        {
          "representative": "Tokuda, Jill",
          "state": "HI"
        },
        {
          "representative": "Fulcher, Russ",
          "state": "ID"
        },
        {
          "representative": "Simpson, Michael",
          "state": "ID"
        },
        {
          "representative": "Jackson, Jonathan",
          "state": "IL"
        },
        {
          "representative": "Kelly, Robin",
          "state": "IL"
        },
        {
          "representative": "Ramirez, Delia",
          "state": "IL"
        },
        {
          "representative": "Garcia, Jesus",
          "state": "IL"
        },
        {
          "representative": "Quigley, Mike",
          "state": "IL"
        },
        {
          "representative": "Casten, Sean",
          "state": "IL"
        },
        {
          "representative": "Davis, Danny",
          "state": "IL"
        },
        {
          "representative": "Krishnamoorthi, Raja",
          "state": "IL"
        },
        {
          "representative": "Schakowsky, Janice",
          "state": "IL"
        },
        {
          "representative": "Schneider, Bradley",
          "state": "IL"
        },
        {
          "representative": "Foster, Bill",
          "state": "IL"
        },
        {
          "representative": "Bost, Mike",
          "state": "IL"
        },
        {
          "representative": "Budzinski, Nikki",
          "state": "IL"
        },
        {
          "representative": "Underwood, Lauren",
          "state": "IL"
        },
        {
          "representative": "Miller, Mary",
          "state": "IL"
        },
        {
          "representative": "LaHood, Darin",
          "state": "IL"
        },
        {
          "representative": "Sorensen, Eric",
          "state": "IL"
        },
        {
          "representative": "Mrvan, Frank",
          "state": "IN"
        },
        {
          "representative": "Yakym, Rudy",
          "state": "IN"
        },
        {
          "representative": "Stutzman, Marlin",
          "state": "IN"
        },
        {
          "representative": "Baird, James",
          "state": "IN"
        },
        {
          "representative": "Spartz, Victoria",
          "state": "IN"
        },
        {
          "representative": "Shreve, Jefferson",
          "state": "IN"
        },
        {
          "representative": "Carson, Andre",
          "state": "IN"
        },
        {
          "representative": "Messmer, Mark",
          "state": "IN"
        },
        {
          "representative": "Houchin, Erin",
          "state": "IN"
        },
        {
          "representative": "Miller-Meeks, Mariannette",
          "state": "IA"
        },
        {
          "representative": "Hinson, Ashley",
          "state": "IA"
        },
        {
          "representative": "Nunn, Zachary",
          "state": "IA"
        },
        {
          "representative": "Feenstra, Randy",
          "state": "IA"
        },
        {
          "representative": "Mann, Tracey",
          "state": "KS"
        },
        {
          "representative": "Schmidt, Derek",
          "state": "KS"
        },
        {
          "representative": "Davids, Sharice",
          "state": "KS"
        },
        {
          "representative": "Estes, Ron",
          "state": "KS"
        },
        {
          "representative": "Comer, James",
          "state": "KY"
        },
        {
          "representative": "Guthrie, Brett",
          "state": "KY"
        },
        {
          "representative": "McGarvey, Morgan",
          "state": "KY"
        },
        {
          "representative": "Massie, Thomas",
          "state": "KY"
        },
        {
          "representative": "Rogers, Harold",
          "state": "KY"
        },
        {
          "representative": "Barr, Andy",
          "state": "KY"
        },
        {
          "representative": "Scalise, Steve",
          "state": "LA"
        },
        {
          "representative": "Carter, Troy",
          "state": "LA"
        },
        {
          "representative": "Higgins, Clay",
          "state": "LA"
        },
        {
          "representative": "Johnson, Mike",
          "state": "LA"
        },
        {
          "representative": "Letlow, Julia",
          "state": "LA"
        },
        {
          "representative": "Fields, Cleo",
          "state": "LA"
        },
        {
          "representative": "Pingree, Chellie",
          "state": "ME"
        },
        {
          "representative": "Golden, Jared",
          "state": "ME"
        },
        {
          "representative": "Harris, Andy",
          "state": "MD"
        },
        {
          "representative": "Olszewski, Johnny",
          "state": "MD"
        },
        {
          "representative": "Elfreth, Sarah",
          "state": "MD"
        },
        {
          "representative": "Ivey, Glenn",
          "state": "MD"
        },
        {
          "representative": "Hoyer, Steny",
          "state": "MD"
        },
        {
          "representative": "McClain Delaney, April",
          "state": "MD"
        },
        {
          "representative": "Mfume, Kweisi",
          "state": "MD"
        },
        {
          "representative": "Raskin, Jamie",
          "state": "MD"
        },
        {
          "representative": "Neal, Richard",
          "state": "MA"
        },
        {
          "representative": "McGovern, James",
          "state": "MA"
        },
        {
          "representative": "Trahan, Lori",
          "state": "MA"
        },
        {
          "representative": "Auchincloss, Jake",
          "state": "MA"
        },
        {
          "representative": "Clark, Katherine",
          "state": "MA"
        },
        {
          "representative": "Moulton, Seth",
          "state": "MA"
        },
        {
          "representative": "Pressley, Ayanna",
          "state": "MA"
        },
        {
          "representative": "Lynch, Stephen",
          "state": "MA"
        },
        {
          "representative": "Keating, William",
          "state": "MA"
        },
        {
          "representative": "Bergman, Jack",
          "state": "MI"
        },
        {
          "representative": "Moolenaar, John",
          "state": "MI"
        },
        {
          "representative": "Scholten, Hillary",
          "state": "MI"
        },
        {
          "representative": "Huizenga, Bill",
          "state": "MI"
        },
        {
          "representative": "Walberg, Tim",
          "state": "MI"
        },
        {
          "representative": "Dingell, Debbie",
          "state": "MI"
        },
        {
          "representative": "Barrett, Tom",
          "state": "MI"
        },
        {
          "representative": "McDonald Rivet, Kristen",
          "state": "MI"
        },
        {
          "representative": "McClain, Lisa",
          "state": "MI"
        },
        {
          "representative": "James, John",
          "state": "MI"
        },
        {
          "representative": "Stevens, Haley",
          "state": "MI"
        },
        {
          "representative": "Tlaib, Rashida",
          "state": "MI"
        },
        {
          "representative": "Thanedar, Shri",
          "state": "MI"
        },
        {
          "representative": "Finstad, Brad",
          "state": "MN"
        },
        {
          "representative": "Craig, Angie",
          "state": "MN"
        },
        {
          "representative": "Morrison, Kelly",
          "state": "MN"
        },
        {
          "representative": "McCollum, Betty",
          "state": "MN"
        },
        {
          "representative": "Omar, Ilhan",
          "state": "MN"
        },
        {
          "representative": "Emmer, Tom",
          "state": "MN"
        },
        {
          "representative": "Fischbach, Michelle",
          "state": "MN"
        },
        {
          "representative": "Stauber, Pete",
          "state": "MN"
        },
        {
          "representative": "Kelly, Trent",
          "state": "MS"
        },
        {
          "representative": "Thompson, Bennie",
          "state": "MS"
        },
        {
          "representative": "Guest, Michael",
          "state": "MS"
        },
        {
          "representative": "Ezell, Mike",
          "state": "MS"
        },
        {
          "representative": "Bell, Wesley",
          "state": "MO"
        },
        {
          "representative": "Wagner, Ann",
          "state": "MO"
        },
        {
          "representative": "Onder, Robert",
          "state": "MO"
        },
        {
          "representative": "Alford, Mark",
          "state": "MO"
        },
        {
          "representative": "Cleaver, Emanuel",
          "state": "MO"
        },
        {
          "representative": "Graves, Sam",
          "state": "MO"
        },
        {
          "representative": "Burlison, Eric",
          "state": "MO"
        },
        {
          "representative": "Smith, Jason",
          "state": "MO"
        },
        {
          "representative": "Zinke, Ryan",
          "state": "MT"
        },
        {
          "representative": "Downing, Troy",
          "state": "MT"
        },
        {
          "representative": "Flood, Mike",
          "state": "NE"
        },
        {
          "representative": "Bacon, Don",
          "state": "NE"
        },
        {
          "representative": "Smith, Adrian",
          "state": "NE"
        },
        {
          "representative": "Titus, Dina",
          "state": "NV"
        },
        {
          "representative": "Amodei, Mark",
          "state": "NV"
        },
        {
          "representative": "Lee, Susie",
          "state": "NV"
        },
        {
          "representative": "Horsford, Steven",
          "state": "NV"
        },
        {
          "representative": "Pappas, Chris",
          "state": "NH"
        },
        {
          "representative": "Goodlander, Maggie",
          "state": "NH"
        },
        {
          "representative": "Norcross, Donald",
          "state": "NJ"
        },
        {
          "representative": "Van Drew, Jefferson",
          "state": "NJ"
        },
        {
          "representative": "Conaway, Herbert",
          "state": "NJ"
        },
        {
          "representative": "Smith, Christopher",
          "state": "NJ"
        },
        {
          "representative": "Gottheimer, Josh",
          "state": "NJ"
        },
        {
          "representative": "Pallone, Frank",
          "state": "NJ"
        },
        {
          "representative": "Kean, Thomas",
          "state": "NJ"
        },
        {
          "representative": "Menendez, Robert",
          "state": "NJ"
        },
        {
          "representative": "Pou, Nellie",
          "state": "NJ"
        },
        {
          "representative": "McIver, LaMonica",
          "state": "NJ"
        },
        {
          "representative": "Sherrill, Mikie",
          "state": "NJ"
        },
        {
          "representative": "Watson Coleman, Bonnie",
          "state": "NJ"
        },
        {
          "representative": "Stansbury, Melanie",
          "state": "NM"
        },
        {
          "representative": "Vasquez, Gabe",
          "state": "NM"
        },
        {
          "representative": "Leger Fernandez, Teresa",
          "state": "NM"
        },
        {
          "representative": "LaLota, Nick",
          "state": "NY"
        },
        {
          "representative": "Garbarino, Andrew",
          "state": "NY"
        },
        {
          "representative": "Suozzi, Thomas R.",
          "state": "NY"
        },
        {
          "representative": "Gillen, Laura",
          "state": "NY"
        },
        {
          "representative": "Meeks, Gregory",
          "state": "NY"
        },
        {
          "representative": "Meng, Grace",
          "state": "NY"
        },
        {
          "representative": "Velazquez, Nydia",
          "state": "NY"
        },
        {
          "representative": "Jeffries, Hakeem",
          "state": "NY"
        },
        {
          "representative": "Clarke, Yvette",
          "state": "NY"
        },
        {
          "representative": "Goldman, Daniel",
          "state": "NY"
        },
        {
          "representative": "Malliotakis, Nicole",
          "state": "NY"
        },
        {
          "representative": "Nadler, Jerrold",
          "state": "NY"
        },
        {
          "representative": "Espaillat, Adriano",
          "state": "NY"
        },
        {
          "representative": "Ocasio-Cortez, Alexandria",
          "state": "NY"
        },
        {
          "representative": "Torres, Ritchie",
          "state": "NY"
        },
        {
          "representative": "Latimer, George",
          "state": "NY"
        },
        {
          "representative": "Lawler, Michael",
          "state": "NY"
        },
        {
          "representative": "Ryan, Patrick",
          "state": "NY"
        },
        {
          "representative": "Riley, Josh",
          "state": "NY"
        },
        {
          "representative": "Tonko, Paul",
          "state": "NY"
        },
        {
          "representative": "Stefanik, Elise",
          "state": "NY"
        },
        {
          "representative": "Mannion, John",
          "state": "NY"
        },
        {
          "representative": "Langworthy, Nicholas",
          "state": "NY"
        },
        {
          "representative": "Tenney, Claudia",
          "state": "NY"
        },
        {
          "representative": "Morelle, Joseph",
          "state": "NY"
        },
        {
          "representative": "Kennedy, Timothy",
          "state": "NY"
        },
        {
          "representative": "Davis, Donald",
          "state": "NC"
        },
        {
          "representative": "Ross, Deborah",
          "state": "NC"
        },
        {
          "representative": "Murphy, Gregory",
          "state": "NC"
        },
        {
          "representative": "Foushee, Valerie",
          "state": "NC"
        },
        {
          "representative": "Foxx, Virginia",
          "state": "NC"
        },
        {
          "representative": "McDowell, Addison",
          "state": "NC"
        },
        {
          "representative": "Rouzer, David",
          "state": "NC"
        },
        {
          "representative": "Harris, Mark",
          "state": "NC"
        },
        {
          "representative": "Hudson, Richard",
          "state": "NC"
        },
        {
          "representative": "Harrigan, Pat",
          "state": "NC"
        },
        {
          "representative": "Edwards, Chuck",
          "state": "NC"
        },
        {
          "representative": "Adams, Alma",
          "state": "NC"
        },
        {
          "representative": "Knott, Brad",
          "state": "NC"
        },
        {
          "representative": "Moore, Tim",
          "state": "NC"
        },
        {
          "representative": "Fedorchak, Julie",
          "state": "ND"
        },
        {
          "representative": "King-Hinds, Kimberlyn",
          "state": "MP"
        },
        {
          "representative": "Landsman, Greg",
          "state": "OH"
        },
        {
          "representative": "Taylor, David",
          "state": "OH"
        },
        {
          "representative": "Beatty, Joyce",
          "state": "OH"
        },
        {
          "representative": "Jordan, Jim",
          "state": "OH"
        },
        {
          "representative": "Latta, Robert",
          "state": "OH"
        },
        {
          "representative": "Rulli, Michael A.",
          "state": "OH"
        },
        {
          "representative": "Miller, Max",
          "state": "OH"
        },
        {
          "representative": "Davidson, Warren",
          "state": "OH"
        },
        {
          "representative": "Kaptur, Marcy",
          "state": "OH"
        },
        {
          "representative": "Turner, Michael",
          "state": "OH"
        },
        {
          "representative": "Brown, Shontel",
          "state": "OH"
        },
        {
          "representative": "Balderson, Troy",
          "state": "OH"
        },
        {
          "representative": "Sykes, Emilia",
          "state": "OH"
        },
        {
          "representative": "Joyce, David",
          "state": "OH"
        },
        {
          "representative": "Carey, Mike",
          "state": "OH"
        },
        {
          "representative": "Hern, Kevin",
          "state": "OK"
        },
        {
          "representative": "Brecheen, Josh",
          "state": "OK"
        },
        {
          "representative": "Lucas, Frank",
          "state": "OK"
        },
        {
          "representative": "Cole, Tom",
          "state": "OK"
        },
        {
          "representative": "Bice, Stephanie",
          "state": "OK"
        },
        {
          "representative": "Bonamici, Suzanne",
          "state": "OR"
        },
        {
          "representative": "Bentz, Cliff",
          "state": "OR"
        },
        {
          "representative": "Dexter, Maxine",
          "state": "OR"
        },
        {
          "representative": "Hoyle, Val",
          "state": "OR"
        },
        {
          "representative": "Bynum, Janelle",
          "state": "OR"
        },
        {
          "representative": "Salinas, Andrea",
          "state": "OR"
        },
        {
          "representative": "Fitzpatrick, Brian",
          "state": "PA"
        },
        {
          "representative": "Boyle, Brendan",
          "state": "PA"
        },
        {
          "representative": "Evans, Dwight",
          "state": "PA"
        },
        {
          "representative": "Dean, Madeleine",
          "state": "PA"
        },
        {
          "representative": "Scanlon, Mary Gay",
          "state": "PA"
        },
        {
          "representative": "Houlahan, Chrissy",
          "state": "PA"
        },
        {
          "representative": "Mackenzie, Ryan",
          "state": "PA"
        },
        {
          "representative": "Bresnahan, Robert",
          "state": "PA"
        },
        {
          "representative": "Meuser, Daniel",
          "state": "PA"
        },
        {
          "representative": "Perry, Scott",
          "state": "PA"
        },
        {
          "representative": "Smucker, Lloyd",
          "state": "PA"
        },
        {
          "representative": "Lee, Summer",
          "state": "PA"
        },
        {
          "representative": "Joyce, John",
          "state": "PA"
        },
        {
          "representative": "Reschenthaler, Guy",
          "state": "PA"
        },
        {
          "representative": "Thompson, Glenn",
          "state": "PA"
        },
        {
          "representative": "Kelly, Mike",
          "state": "PA"
        },
        {
          "representative": "Deluzio, Christopher",
          "state": "PA"
        },
        {
          "representative": "Hernandez, Pablo",
          "state": "PR"
        },
        {
          "representative": "Amo, Gabe",
          "state": "RI"
        },
        {
          "representative": "Magaziner, Seth",
          "state": "RI"
        },
        {
          "representative": "Mace, Nancy",
          "state": "SC"
        },
        {
          "representative": "Wilson, Joe",
          "state": "SC"
        },
        {
          "representative": "Biggs, Sheri",
          "state": "SC"
        },
        {
          "representative": "Timmons, William",
          "state": "SC"
        },
        {
          "representative": "Norman, Ralph",
          "state": "SC"
        },
        {
          "representative": "Clyburn, James",
          "state": "SC"
        },
        {
          "representative": "Fry, Russell",
          "state": "SC"
        },
        {
          "representative": "Johnson, Dusty",
          "state": "SD"
        },
        {
          "representative": "Harshbarger, Diana",
          "state": "TN"
        },
        {
          "representative": "Burchett, Tim",
          "state": "TN"
        },
        {
          "representative": "Fleischmann, Charles",
          "state": "TN"
        },
        {
          "representative": "DesJarlais, Scott",
          "state": "TN"
        },
        {
          "representative": "Ogles, Andrew",
          "state": "TN"
        },
        {
          "representative": "Rose, John",
          "state": "TN"
        },
        {
          "representative": "Green, Mark E.- Vacancy",
          "state": "TN"
        },
        {
          "representative": "Kustoff, David",
          "state": "TN"
        },
        {
          "representative": "Cohen, Steve",
          "state": "TN"
        },
        {
          "representative": "Moran, Nathaniel",
          "state": "TX"
        },
        {
          "representative": "Crenshaw, Dan",
          "state": "TX"
        },
        {
          "representative": "Self, Keith",
          "state": "TX"
        },
        {
          "representative": "Fallon, Pat",
          "state": "TX"
        },
        {
          "representative": "Gooden, Lance",
          "state": "TX"
        },
        {
          "representative": "Ellzey, Jake",
          "state": "TX"
        },
        {
          "representative": "Fletcher, Lizzie",
          "state": "TX"
        },
        {
          "representative": "Luttrell, Morgan",
          "state": "TX"
        },
        {
          "representative": "Green, Al",
          "state": "TX"
        },
        {
          "representative": "McCaul, Michael",
          "state": "TX"
        },
        {
          "representative": "Pfluger, August",
          "state": "TX"
        },
        {
          "representative": "Goldman, Craig",
          "state": "TX"
        },
        {
          "representative": "Jackson, Ronny",
          "state": "TX"
        },
        {
          "representative": "Weber, Randy",
          "state": "TX"
        },
        {
          "representative": "De La Cruz, Monica",
          "state": "TX"
        },
        {
          "representative": "Escobar, Veronica",
          "state": "TX"
        },
        {
          "representative": "Sessions, Pete",
          "state": "TX"
        },
        {
          "representative": "Turner, Sylvester- Vacancy",
          "state": "TX"
        },
        {
          "representative": "Arrington, Jodey",
          "state": "TX"
        },
        {
          "representative": "Castro, Joaquin",
          "state": "TX"
        },
        {
          "representative": "Roy, Chip",
          "state": "TX"
        },
        {
          "representative": "Nehls, Troy",
          "state": "TX"
        },
        {
          "representative": "Gonzales, Tony",
          "state": "TX"
        },
        {
          "representative": "Van Duyne, Beth",
          "state": "TX"
        },
        {
          "representative": "Williams, Roger",
          "state": "TX"
        },
        {
          "representative": "Gill, Brandon",
          "state": "TX"
        },
        {
          "representative": "Cloud, Michael",
          "state": "TX"
        },
        {
          "representative": "Cuellar, Henry",
          "state": "TX"
        },
        {
          "representative": "Garcia, Sylvia",
          "state": "TX"
        },
        {
          "representative": "Crockett, Jasmine",
          "state": "TX"
        },
        {
          "representative": "Carter, John",
          "state": "TX"
        },
        {
          "representative": "Johnson, Julie",
          "state": "TX"
        },
        {
          "representative": "Veasey, Marc",
          "state": "TX"
        },
        {
          "representative": "Gonzalez, Vicente",
          "state": "TX"
        },
        {
          "representative": "Casar, Greg",
          "state": "TX"
        },
        {
          "representative": "Babin, Brian",
          "state": "TX"
        },
        {
          "representative": "Doggett, Lloyd",
          "state": "TX"
        },
        {
          "representative": "Hunt, Wesley",
          "state": "TX"
        },
        {
          "representative": "Moore, Blake",
          "state": "UT"
        },
        {
          "representative": "Maloy, Celeste",
          "state": "UT"
        },
        {
          "representative": "Kennedy, Mike",
          "state": "UT"
        },
        {
          "representative": "Owens, Burgess",
          "state": "UT"
        },
        {
          "representative": "Balint, Becca",
          "state": "VT"
        },
        {
          "representative": "Wittman, Robert",
          "state": "VA"
        },
        {
          "representative": "Kiggans, Jennifer",
          "state": "VA"
        },
        {
          "representative": "Scott, Robert",
          "state": "VA"
        },
        {
          "representative": "McClellan, Jennifer",
          "state": "VA"
        },
        {
          "representative": "McGuire, John",
          "state": "VA"
        },
        {
          "representative": "Cline, Ben",
          "state": "VA"
        },
        {
          "representative": "Vindman, Eugene",
          "state": "VA"
        },
        {
          "representative": "Beyer, Donald",
          "state": "VA"
        },
        {
          "representative": "Griffith, H.",
          "state": "VA"
        },
        {
          "representative": "Subramanyam, Suhas",
          "state": "VA"
        },
        {
          "representative": "Connolly, Gerald E.- Vacancy",
          "state": "VA"
        },
        {
          "representative": "Plaskett, Stacey",
          "state": "VI"
        },
        {
          "representative": "DelBene, Suzan",
          "state": "WA"
        },
        {
          "representative": "Larsen, Rick",
          "state": "WA"
        },
        {
          "representative": "Perez, Marie",
          "state": "WA"
        },
        {
          "representative": "Newhouse, Dan",
          "state": "WA"
        },
        {
          "representative": "Baumgartner, Michael",
          "state": "WA"
        },
        {
          "representative": "Randall, Emily",
          "state": "WA"
        },
        {
          "representative": "Jayapal, Pramila",
          "state": "WA"
        },
        {
          "representative": "Schrier, Kim",
          "state": "WA"
        },
        {
          "representative": "Smith, Adam",
          "state": "WA"
        },
        {
          "representative": "Strickland, Marilyn",
          "state": "WA"
        },
        {
          "representative": "Miller, Carol",
          "state": "WV"
        },
        {
          "representative": "Moore, Riley",
          "state": "WV"
        },
        {
          "representative": "Steil, Bryan",
          "state": "WI"
        },
        {
          "representative": "Pocan, Mark",
          "state": "WI"
        },
        {
          "representative": "Van Orden, Derrick",
          "state": "WI"
        },
        {
          "representative": "Moore, Gwen",
          "state": "WI"
        },
        {
          "representative": "Fitzgerald, Scott",
          "state": "WI"
        },
        {
          "representative": "Grothman, Glenn",
          "state": "WI"
        },
        {
          "representative": "Tiffany, Thomas",
          "state": "WI"
        },
        {
          "representative": "Wied, Tony",
          "state": "WI"
        },
        {
          "representative": "Hageman, Harriet",
          "state": "WY"
        }
      ]
    }
  },
  {
    "theme": "AMERICAN GOVERNMENT",
    "section": "System of Government",
    "question": "Who does a U.S. Senator represent?",
    "questionNumber": 24,
    "expectedAnswers": 1,
    "answers": {
      "_type": "text",
      "choices": [
        "all people of the state"
      ]
    }
  },
  {
    "theme": "AMERICAN GOVERNMENT",
    "section": "System of Government",
    "question": "Why do some states have more Representatives than other states?",
    "questionNumber": 25,
    "expectedAnswers": 1,
    "answers": {
      "_type": "text",
      "choices": [
        "(because of) the state's population",
        "(because) they have more people",
        "(because) some states have more people"
      ]
    }
  },
  {
    "theme": "AMERICAN GOVERNMENT",
    "section": "System of Government",
    "question": "We elect a President for how many years?",
    "questionNumber": 26,
    "expectedAnswers": 1,
    "answers": {
      "_type": "text",
      "choices": [
        "four (4)"
      ]
    }
  },
  {
    "theme": "AMERICAN GOVERNMENT",
    "section": "System of Government",
    "question": "In what month do we vote for President?*",
    "questionNumber": 27,
    "expectedAnswers": 1,
    "answers": {
      "_type": "text",
      "choices": [
        "November"
      ]
    }
  },
  {
    "theme": "AMERICAN GOVERNMENT",
    "section": "System of Government",
    "question": "What is the name of the President of the United States now?*",
    "questionNumber": 28,
    "expectedAnswers": 1,
    "answers": {
      "_type": "text",
      "choices": [
        "Donald J. Trump",
        "Donald Trump",
        "Trump"
      ]
    }
  },
  {
    "theme": "AMERICAN GOVERNMENT",
    "section": "System of Government",
    "question": "What is the name of the Vice President of the United States now?",
    "questionNumber": 29,
    "expectedAnswers": 1,
    "answers": {
      "_type": "text",
      "choices": [
        "JD Vance",
        "Vance"
      ]
    }
  },
  {
    "theme": "AMERICAN GOVERNMENT",
    "section": "System of Government",
    "question": "If the President can no longer serve, who becomes President?",
    "questionNumber": 30,
    "expectedAnswers": 1,
    "answers": {
      "_type": "text",
      "choices": [
        "the Vice President"
      ]
    }
  },
  {
    "theme": "AMERICAN GOVERNMENT",
    "section": "System of Government",
    "question": "If both the President and the Vice President can no longer serve, who becomes President?",
    "questionNumber": 31,
    "expectedAnswers": 1,
    "answers": {
      "_type": "text",
      "choices": [
        "the Speaker of the House"
      ]
    }
  },
  {
    "theme": "AMERICAN GOVERNMENT",
    "section": "System of Government",
    "question": "Who is the Commander in Chief of the military?",
    "questionNumber": 32,
    "expectedAnswers": 1,
    "answers": {
      "_type": "text",
      "choices": [
        "the President"
      ]
    }
  },
  {
    "theme": "AMERICAN GOVERNMENT",
    "section": "System of Government",
    "question": "Who signs bills to become laws?",
    "questionNumber": 33,
    "expectedAnswers": 1,
    "answers": {
      "_type": "text",
      "choices": [
        "the President"
      ]
    }
  },
  {
    "theme": "AMERICAN GOVERNMENT",
    "section": "System of Government",
    "question": "Who vetoes bills?",
    "questionNumber": 34,
    "expectedAnswers": 1,
    "answers": {
      "_type": "text",
      "choices": [
        "the President"
      ]
    }
  },
  {
    "theme": "AMERICAN GOVERNMENT",
    "section": "System of Government",
    "question": "What does the President's Cabinet do?",
    "questionNumber": 35,
    "expectedAnswers": 1,
    "answers": {
      "_type": "text",
      "choices": [
        "advises the President"
      ]
    }
  },
  {
    "theme": "AMERICAN GOVERNMENT",
    "section": "System of Government",
    "question": "What are two Cabinet-level positions?",
    "questionNumber": 36,
    "expectedAnswers": 2,
    "answers": {
      "_type": "text",
      "choices": [
        "Secretary of Agriculture",
        "Secretary of Commerce",
        "Secretary of Defense",
        "Secretary of Education",
        "Secretary of Energy",
        "Secretary of Health and Human Services",
        "Secretary of Homeland Security",
        "Secretary of Housing and Urban Development",
        "Secretary of the Interior",
        "Secretary of Labor",
        "Secretary of State",
        "Secretary of Transportation",
        "Secretary of the Treasury",
        "Secretary of Veterans Affairs",
        "Attorney General",
        "Vice President"
      ]
    }
  },
  {
    "theme": "AMERICAN GOVERNMENT",
    "section": "System of Government",
    "question": "What does the judicial branch do?",
    "questionNumber": 37,
    "expectedAnswers": 1,
    "answers": {
      "_type": "text",
      "choices": [
        "reviews laws",
        "explains laws",
        "resolves disputes (disagreements)",
        "decides if a law goes against the Constitution"
      ]
    }
  },
  {
    "theme": "AMERICAN GOVERNMENT",
    "section": "System of Government",
    "question": "What is the highest court in the United States?",
    "questionNumber": 38,
    "expectedAnswers": 1,
    "answers": {
      "_type": "text",
      "choices": [
        "the Supreme Court"
      ]
    }
  },
  {
    "theme": "AMERICAN GOVERNMENT",
    "section": "System of Government",
    "question": "How many justices are on the Supreme Court?",
    "questionNumber": 39,
    "expectedAnswers": 1,
    "answers": {
      "_type": "text",
      "choices": [
        "nine (9)"
      ]
    }
  },
  {
    "theme": "AMERICAN GOVERNMENT",
    "section": "System of Government",
    "question": "Who is the Chief Justice of the United States now?",
    "questionNumber": 40,
    "expectedAnswers": 1,
    "answers": {
      "_type": "text",
      "choices": [
        "John Roberts",
        "John G. Roberts, Jr."
      ]
    }
  },
  {
    "theme": "AMERICAN GOVERNMENT",
    "section": "System of Government",
    "question": "Under our Constitution, some powers belong to the federal government. What is one power of the federal government?",
    "questionNumber": 41,
    "expectedAnswers": 1,
    "answers": {
      "_type": "text",
      "choices": [
        "to print money",
        "to declare war",
        "to create an army",
        "to make treaties"
      ]
    }
  },
  {
    "theme": "AMERICAN GOVERNMENT",
    "section": "System of Government",
    "question": "Under our Constitution, some powers belong to the states. What is one power of the states?",
    "questionNumber": 42,
    "expectedAnswers": 1,
    "answers": {
      "_type": "text",
      "choices": [
        "provide schooling and education",
        "provide protection (police)",
        "provide safety (fire departments)",
        "give a driver's license",
        "approve zoning and land use"
      ]
    }
  },
  {
    "theme": "AMERICAN GOVERNMENT",
    "section": "System of Government",
    "question": "Who is the Governor of your state now?",
    "questionNumber": 43,
    "expectedAnswers": 1,
    "answers": {
      "_type": "governor",
      "choices": [
        {
          "governor": "Mike Dunleavy",
          "state": "AK"
        },
        {
          "governor": "Kay Ivey",
          "state": "AL"
        },
        {
          "governor": "Sarah Huckabee Sanders",
          "state": "AR"
        },
        {
          "governor": "Pula’ali’i Nikolao Pula",
          "state": "AS"
        },
        {
          "governor": "Katie Hobbs",
          "state": "AZ"
        },
        {
          "governor": "Gavin Newsom",
          "state": "CA"
        },
        {
          "governor": "Jared Polis",
          "state": "CO"
        },
        {
          "governor": "Ned Lamont",
          "state": "CT"
        },
        {
          "governor": "D.C. does not have a Governor, but the Mayor is Muriel Bowser",
          "state": "DC"
        },
        {
          "governor": "Matt Meyer",
          "state": "DE"
        },
        {
          "governor": "Ron DeSantis",
          "state": "FL"
        },
        {
          "governor": "Brian P. Kemp",
          "state": "GA"
        },
        {
          "governor": "Lourdes Aflague Leon Guerrero",
          "state": "GU"
        },
        {
          "governor": "Josh Green",
          "state": "HI"
        },
        {
          "governor": "Kim Reynolds",
          "state": "IA"
        },
        {
          "governor": "Brad Little",
          "state": "ID"
        },
        {
          "governor": "JB Pritzker",
          "state": "IL"
        },
        {
          "governor": "Mike Braun",
          "state": "IN"
        },
        {
          "governor": "Laura Kelly",
          "state": "KS"
        },
        {
          "governor": "Andy Beshear",
          "state": "KY"
        },
        {
          "governor": "Jeff Landry",
          "state": "LA"
        },
        {
          "governor": "Maura Healey",
          "state": "MA"
        },
        {
          "governor": "Wes Moore",
          "state": "MD"
        },
        {
          "governor": "Janet T. Mills",
          "state": "ME"
        },
        {
          "governor": "Gretchen Whitmer",
          "state": "MI"
        },
        {
          "governor": "Tim Walz",
          "state": "MN"
        },
        {
          "governor": "Mike Kehoe",
          "state": "MO"
        },
        {
          "governor": "Arnold Palacios",
          "state": "MP"
        },
        {
          "governor": "Tate Reeves",
          "state": "MS"
        },
        {
          "governor": "Greg Gianforte",
          "state": "MT"
        },
        {
          "governor": "Josh Stein",
          "state": "NC"
        },
        {
          "governor": "Kelly Armstrong",
          "state": "ND"
        },
        {
          "governor": "Jim Pillen",
          "state": "NE"
        },
        {
          "governor": "Kelly Ayotte",
          "state": "NH"
        },
        {
          "governor": "Phil Murphy",
          "state": "NJ"
        },
        {
          "governor": "Michelle Lujan Grisham",
          "state": "NM"
        },
        {
          "governor": "Joe Lombardo",
          "state": "NV"
        },
        {
          "governor": "Kathy Hochul",
          "state": "NY"
        },
        {
          "governor": "Mike DeWine",
          "state": "OH"
        },
        {
          "governor": "J. Kevin Stitt",
          "state": "OK"
        },
        {
          "governor": "Tina Kotek",
          "state": "OR"
        },
        {
          "governor": "Josh Shapiro",
          "state": "PA"
        },
        {
          "governor": "Jenniffer González-Colón",
          "state": "PR"
        },
        {
          "governor": "Dan McKee",
          "state": "RI"
        },
        {
          "governor": "Henry McMaster",
          "state": "SC"
        },
        {
          "governor": "Larry Rhoden",
          "state": "SD"
        },
        {
          "governor": "Bill Lee",
          "state": "TN"
        },
        {
          "governor": "Greg Abbott",
          "state": "TX"
        },
        {
          "governor": "Spencer J. Cox",
          "state": "UT"
        },
        {
          "governor": "Glenn Youngkin",
          "state": "VA"
        },
        {
          "governor": "Albert Bryan Jr.",
          "state": "VI"
        },
        {
          "governor": "Phil Scott",
          "state": "VT"
        },
        {
          "governor": "Bob Ferguson",
          "state": "WA"
        },
        {
          "governor": "Tony Evers",
          "state": "WI"
        },
        {
          "governor": "Patrick Morrisey",
          "state": "WV"
        },
        {
          "governor": "Mark Gordon",
          "state": "WY"
        }
      ]
    }
  },
  {
    "theme": "AMERICAN GOVERNMENT",
    "section": "System of Government",
    "question": "What is the capital of your state?*",
    "questionNumber": 44,
    "expectedAnswers": 1,
    "answers": {
      "_type": "capital",
      "choices": [
        {
          "capital": "Montgomery",
          "state": "AL"
        },
        {
          "capital": "Juneau",
          "state": "AK"
        },
        {
          "capital": "Phoenix",
          "state": "AZ"
        },
        {
          "capital": "Little Rock",
          "state": "AR"
        },
        {
          "capital": "Sacramento",
          "state": "CA"
        },
        {
          "capital": "Denver",
          "state": "CO"
        },
        {
          "capital": "Hartford",
          "state": "CT"
        },
        {
          "capital": "Dover",
          "state": "DE"
        },
        {
          "capital": "Tallahassee",
          "state": "FL"
        },
        {
          "capital": "Atlanta",
          "state": "GA"
        },
        {
          "capital": "Honolulu",
          "state": "HI"
        },
        {
          "capital": "Boise",
          "state": "ID"
        },
        {
          "capital": "Springfield",
          "state": "IL"
        },
        {
          "capital": "Indianapolis",
          "state": "IN"
        },
        {
          "capital": "Des Moines",
          "state": "IA"
        },
        {
          "capital": "Topeka",
          "state": "KS"
        },
        {
          "capital": "Frankfort",
          "state": "KY"
        },
        {
          "capital": "Baton Rouge",
          "state": "LA"
        },
        {
          "capital": "Augusta",
          "state": "ME"
        },
        {
          "capital": "Annapolis",
          "state": "MD"
        },
        {
          "capital": "Boston",
          "state": "MA"
        },
        {
          "capital": "Lansing",
          "state": "MI"
        },
        {
          "capital": "Saint Paul",
          "state": "MN"
        },
        {
          "capital": "Jackson",
          "state": "MS"
        },
        {
          "capital": "Jefferson City",
          "state": "MO"
        },
        {
          "capital": "Helena",
          "state": "MT"
        },
        {
          "capital": "Lincoln",
          "state": "NE"
        },
        {
          "capital": "Carson City",
          "state": "NV"
        },
        {
          "capital": "Concord",
          "state": "NH"
        },
        {
          "capital": "Trenton",
          "state": "NJ"
        },
        {
          "capital": "Santa Fe",
          "state": "NM"
        },
        {
          "capital": "Albany",
          "state": "NY"
        },
        {
          "capital": "Raleigh",
          "state": "NC"
        },
        {
          "capital": "Bismarck",
          "state": "ND"
        },
        {
          "capital": "Columbus",
          "state": "OH"
        },
        {
          "capital": "Oklahoma City",
          "state": "OK"
        },
        {
          "capital": "Salem",
          "state": "OR"
        },
        {
          "capital": "Harrisburg",
          "state": "PA"
        },
        {
          "capital": "Providence",
          "state": "RI"
        },
        {
          "capital": "Columbia",
          "state": "SC"
        },
        {
          "capital": "Pierre",
          "state": "SD"
        },
        {
          "capital": "Nashville",
          "state": "TN"
        },
        {
          "capital": "Austin",
          "state": "TX"
        },
        {
          "capital": "Salt Lake City",
          "state": "UT"
        },
        {
          "capital": "Montpelier",
          "state": "VT"
        },
        {
          "capital": "Richmond",
          "state": "VA"
        },
        {
          "capital": "Olympia",
          "state": "WA"
        },
        {
          "capital": "Charleston",
          "state": "WV"
        },
        {
          "capital": "Madison",
          "state": "WI"
        },
        {
          "capital": "Cheyenne",
          "state": "WY"
        },
        {
          "capital": "D.C. is not a state and does not have a capital",
          "state": "DC"
        },
        {
          "capital": "Pago Pago",
          "state": "AS"
        },
        {
          "capital": "Hagatna",
          "state": "GU"
        },
        {
          "capital": "Saipan",
          "state": "MP"
        },
        {
          "capital": "San Juan",
          "state": "PR"
        },
        {
          "capital": "Charlotte Amalie",
          "state": "VI"
        }
      ]
    }
  },
  {
    "theme": "AMERICAN GOVERNMENT",
    "section": "System of Government",
    "question": "What are the two major political parties in the United States?*",
    "questionNumber": 45,
    "expectedAnswers": 1,
    "answers": {
      "_type": "text",
      "choices": [
        "Democratic and Republican"
      ]
    }
  },
  {
    "theme": "AMERICAN GOVERNMENT",
    "section": "System of Government",
    "question": "What is the political party of the President now?",
    "questionNumber": 46,
    "expectedAnswers": 1,
    "answers": {
      "_type": "text",
      "choices": [
        "Republican (Party)"
      ]
    }
  },
  {
    "theme": "AMERICAN GOVERNMENT",
    "section": "System of Government",
    "question": "What is the name of the Speaker of the House of Representatives now?",
    "questionNumber": 47,
    "expectedAnswers": 1,
    "answers": {
      "_type": "text",
      "choices": [
        "Mike Johnson",
        "Johnson",
        "James Michael Johnson (birth name)"
      ]
    }
  },
  {
    "theme": "AMERICAN GOVERNMENT",
    "section": "Rights and Responsibilities",
    "question": "There are four amendments to the Constitution about who can vote. Describe one of them.",
    "questionNumber": 48,
    "expectedAnswers": 1,
    "answers": {
      "_type": "text",
      "choices": [
        "Citizens eighteen (18) and older (can vote).",
        "You don't have to pay (a poll tax) to vote.",
        "Any citizen can vote. (Women and men can vote.)",
        "A male citizen of any race (can vote)."
      ]
    }
  },
  {
    "theme": "AMERICAN GOVERNMENT",
    "section": "Rights and Responsibilities",
    "question": "What is one responsibility that is only for United States citizens?*",
    "questionNumber": 49,
    "expectedAnswers": 1,
    "answers": {
      "_type": "text",
      "choices": [
        "serve on a jury",
        "vote in a federal election"
      ]
    }
  },
  {
    "theme": "AMERICAN GOVERNMENT",
    "section": "Rights and Responsibilities",
    "question": "Name one right only for United States citizens.",
    "questionNumber": 50,
    "expectedAnswers": 1,
    "answers": {
      "_type": "text",
      "choices": [
        "vote in a federal election",
        "run for federal office"
      ]
    }
  },
  {
    "theme": "AMERICAN GOVERNMENT",
    "section": "Rights and Responsibilities",
    "question": "What are two rights of everyone living in the United States?",
    "questionNumber": 51,
    "expectedAnswers": 2,
    "answers": {
      "_type": "text",
      "choices": [
        "freedom of expression",
        "freedom of speech",
        "freedom of assembly",
        "freedom to petition the government",
        "freedom of religion",
        "the right to bear arms"
      ]
    }
  },
  {
    "theme": "AMERICAN GOVERNMENT",
    "section": "Rights and Responsibilities",
    "question": "What do we show loyalty to when we say the Pledge of Allegiance?",
    "questionNumber": 52,
    "expectedAnswers": 1,
    "answers": {
      "_type": "text",
      "choices": [
        "the United States",
        "the flag"
      ]
    }
  },
  {
    "theme": "AMERICAN GOVERNMENT",
    "section": "Rights and Responsibilities",
    "question": "What is one promise you make when you become a United States citizen?",
    "questionNumber": 53,
    "expectedAnswers": 1,
    "answers": {
      "_type": "text",
      "choices": [
        "give up loyalty to other countries",
        "defend the Constitution and laws of the United States",
        "obey the laws of the United States",
        "serve in the U.S. military (if needed)",
        "serve (do important work for) the nation (if needed)",
        "be loyal to the United States"
      ]
    }
  },
  {
    "theme": "AMERICAN GOVERNMENT",
    "section": "Rights and Responsibilities",
    "question": "How old do citizens have to be to vote for President?*",
    "questionNumber": 54,
    "expectedAnswers": 1,
    "answers": {
      "_type": "text",
      "choices": [
        "eighteen (18) and older"
      ]
    }
  },
  {
    "theme": "AMERICAN GOVERNMENT",
    "section": "Rights and Responsibilities",
    "question": "What are two ways that Americans can participate in their democracy?",
    "questionNumber": 55,
    "expectedAnswers": 2,
    "answers": {
      "_type": "text",
      "choices": [
        "vote",
        "join a political party",
        "help with a campaign",
        "join a civic group",
        "join a community group",
        "give an elected official your opinion on an issue",
        "call Senators and Representatives",
        "publicly support or oppose an issue or policy",
        "run for office",
        "write to a newspaper"
      ]
    }
  },
  {
    "theme": "AMERICAN GOVERNMENT",
    "section": "Rights and Responsibilities",
    "question": "When is the last day you can send in federal income tax forms?*",
    "questionNumber": 56,
    "expectedAnswers": 1,
    "answers": {
      "_type": "text",
      "choices": [
        "April 15"
      ]
    }
  },
  {
    "theme": "AMERICAN GOVERNMENT",
    "section": "Rights and Responsibilities",
    "question": "When must all men register for the Selective Service?",
    "questionNumber": 57,
    "expectedAnswers": 1,
    "answers": {
      "_type": "text",
      "choices": [
        "at age eighteen (18)",
        "between eighteen (18) and twenty-six (26)"
      ]
    }
  },
  {
    "theme": "AMERICAN HISTORY",
    "section": "Colonial Period and Independence",
    "question": "What is one reason colonists came to America?",
    "questionNumber": 58,
    "expectedAnswers": 1,
    "answers": {
      "_type": "text",
      "choices": [
        "freedom",
        "political liberty",
        "religious freedom",
        "economic opportunity",
        "practice their religion",
        "escape persecution"
      ]
    }
  },
  {
    "theme": "AMERICAN HISTORY",
    "section": "Colonial Period and Independence",
    "question": "Who lived in America before the Europeans arrived?",
    "questionNumber": 59,
    "expectedAnswers": 1,
    "answers": {
      "_type": "text",
      "choices": [
        "American Indians",
        "Native Americans"
      ]
    }
  },
  {
    "theme": "AMERICAN HISTORY",
    "section": "Colonial Period and Independence",
    "question": "What group of people was taken to America and sold as slaves?",
    "questionNumber": 60,
    "expectedAnswers": 1,
    "answers": {
      "_type": "text",
      "choices": [
        "Africans",
        "people from Africa"
      ]
    }
  },
  {
    "theme": "AMERICAN HISTORY",
    "section": "Colonial Period and Independence",
    "question": "Why did the colonists fight the British?",
    "questionNumber": 61,
    "expectedAnswers": 1,
    "answers": {
      "_type": "text",
      "choices": [
        "because of high taxes (taxation without representation)",
        "because the British army stayed in their houses (boarding, quartering)",
        "because they didn't have self-government"
      ]
    }
  },
  {
    "theme": "AMERICAN HISTORY",
    "section": "Colonial Period and Independence",
    "question": "Who wrote the Declaration of Independence?",
    "questionNumber": 62,
    "expectedAnswers": 1,
    "answers": {
      "_type": "text",
      "choices": [
        "(Thomas) Jefferson"
      ]
    }
  },
  {
    "theme": "AMERICAN HISTORY",
    "section": "Colonial Period and Independence",
    "question": "When was the Declaration of Independence adopted?",
    "questionNumber": 63,
    "expectedAnswers": 1,
    "answers": {
      "_type": "text",
      "choices": [
        "July 4, 1776"
      ]
    }
  },
  {
    "theme": "AMERICAN HISTORY",
    "section": "Colonial Period and Independence",
    "question": "There were 13 original states. Name three.",
    "questionNumber": 64,
    "expectedAnswers": 3,
    "answers": {
      "_type": "text",
      "choices": [
        "New Hampshire",
        "Massachusetts",
        "Rhode Island",
        "Connecticut",
        "New York",
        "New Jersey",
        "Pennsylvania",
        "Delaware",
        "Maryland",
        "Virginia",
        "North Carolina",
        "South Carolina",
        "Georgia"
      ]
    }
  },
  {
    "theme": "AMERICAN HISTORY",
    "section": "Colonial Period and Independence",
    "question": "What happened at the Constitutional Convention?",
    "questionNumber": 65,
    "expectedAnswers": 1,
    "answers": {
      "_type": "text",
      "choices": [
        "The Constitution was written.",
        "The Founding Fathers wrote the Constitution."
      ]
    }
  },
  {
    "theme": "AMERICAN HISTORY",
    "section": "Colonial Period and Independence",
    "question": "When was the Constitution written?",
    "questionNumber": 66,
    "expectedAnswers": 1,
    "answers": {
      "_type": "text",
      "choices": [
        "1787"
      ]
    }
  },
  {
    "theme": "AMERICAN HISTORY",
    "section": "Colonial Period and Independence",
    "question": "The Federalist Papers supported the passage of the U.S. Constitution. Name one of the writers.",
    "questionNumber": 67,
    "expectedAnswers": 1,
    "answers": {
      "_type": "text",
      "choices": [
        "(James) Madison",
        "(Alexander) Hamilton",
        "(John) Jay",
        "Publius"
      ]
    }
  },
  {
    "theme": "AMERICAN HISTORY",
    "section": "Colonial Period and Independence",
    "question": "What is one thing Benjamin Franklin is famous for?",
    "questionNumber": 68,
    "expectedAnswers": 1,
    "answers": {
      "_type": "text",
      "choices": [
        "U.S. diplomat",
        "oldest member of the Constitutional Convention",
        "first Postmaster General of the United States",
        "writer of \"Poor Richard's Almanac\"",
        "started the first free libraries"
      ]
    }
  },
  {
    "theme": "AMERICAN HISTORY",
    "section": "Colonial Period and Independence",
    "question": "Who is the \"Father of Our Country\"?",
    "questionNumber": 69,
    "expectedAnswers": 1,
    "answers": {
      "_type": "text",
      "choices": [
        "(George) Washington"
      ]
    }
  },
  {
    "theme": "AMERICAN HISTORY",
    "section": "Colonial Period and Independence",
    "question": "Who was the first President?*",
    "questionNumber": 70,
    "expectedAnswers": 1,
    "answers": {
      "_type": "text",
      "choices": [
        "(George) Washington"
      ]
    }
  },
  {
    "theme": "AMERICAN HISTORY",
    "section": "1800s",
    "question": "What territory did the United States buy from France in 1803?",
    "questionNumber": 71,
    "expectedAnswers": 1,
    "answers": {
      "_type": "text",
      "choices": [
        "the Louisiana Territory",
        "Louisiana"
      ]
    }
  },
  {
    "theme": "AMERICAN HISTORY",
    "section": "1800s",
    "question": "Name one war fought by the United States in the 1800s.",
    "questionNumber": 72,
    "expectedAnswers": 1,
    "answers": {
      "_type": "text",
      "choices": [
        "War of 1812",
        "Mexican-American War",
        "Civil War",
        "Spanish-American War"
      ]
    }
  },
  {
    "theme": "AMERICAN HISTORY",
    "section": "1800s",
    "question": "Name the U.S. war between the North and the South.",
    "questionNumber": 73,
    "expectedAnswers": 1,
    "answers": {
      "_type": "text",
      "choices": [
        "the Civil War",
        "the War between the States"
      ]
    }
  },
  {
    "theme": "AMERICAN HISTORY",
    "section": "1800s",
    "question": "Name one problem that led to the Civil War.",
    "questionNumber": 74,
    "expectedAnswers": 1,
    "answers": {
      "_type": "text",
      "choices": [
        "slavery",
        "economic reasons",
        "states' rights"
      ]
    }
  },
  {
    "theme": "AMERICAN HISTORY",
    "section": "1800s",
    "question": "What was one important thing that Abraham Lincoln did?*",
    "questionNumber": 75,
    "expectedAnswers": 1,
    "answers": {
      "_type": "text",
      "choices": [
        "freed the slaves (Emancipation Proclamation)",
        "saved (or preserved) the Union",
        "led the United States during the Civil War"
      ]
    }
  },
  {
    "theme": "AMERICAN HISTORY",
    "section": "1800s",
    "question": "What did the Emancipation Proclamation do?",
    "questionNumber": 76,
    "expectedAnswers": 1,
    "answers": {
      "_type": "text",
      "choices": [
        "freed the slaves",
        "freed slaves in the Confederacy",
        "freed slaves in the Confederate states",
        "freed slaves in most Southern states"
      ]
    }
  },
  {
    "theme": "AMERICAN HISTORY",
    "section": "1800s",
    "question": "What did Susan B. Anthony do?",
    "questionNumber": 77,
    "expectedAnswers": 1,
    "answers": {
      "_type": "text",
      "choices": [
        "fought for women's rights",
        "fought for civil rights"
      ]
    }
  },
  {
    "theme": "AMERICAN HISTORY",
    "section": "Recent American History and Other Important Historical Information",
    "question": "Name one war fought by the United States in the 1900s.*",
    "questionNumber": 78,
    "expectedAnswers": 1,
    "answers": {
      "_type": "text",
      "choices": [
        "World War I",
        "World War II",
        "Korean War",
        "Vietnam War",
        "(Persian) Gulf War"
      ]
    }
  },
  {
    "theme": "AMERICAN HISTORY",
    "section": "Recent American History and Other Important Historical Information",
    "question": "Who was President during World War I?",
    "questionNumber": 79,
    "expectedAnswers": 1,
    "answers": {
      "_type": "text",
      "choices": [
        "(Woodrow) Wilson"
      ]
    }
  },
  {
    "theme": "AMERICAN HISTORY",
    "section": "Recent American History and Other Important Historical Information",
    "question": "Who was President during the Great Depression and World War II?",
    "questionNumber": 80,
    "expectedAnswers": 1,
    "answers": {
      "_type": "text",
      "choices": [
        "(Franklin) Roosevelt"
      ]
    }
  },
  {
    "theme": "AMERICAN HISTORY",
    "section": "Recent American History and Other Important Historical Information",
    "question": "Who did the United States fight in World War II?",
    "questionNumber": 81,
    "expectedAnswers": 1,
    "answers": {
      "_type": "text",
      "choices": [
        "Japan, Germany, and Italy"
      ]
    }
  },
  {
    "theme": "AMERICAN HISTORY",
    "section": "Recent American History and Other Important Historical Information",
    "question": "Before he was President, Eisenhower was a general. What war was he in?",
    "questionNumber": 82,
    "expectedAnswers": 1,
    "answers": {
      "_type": "text",
      "choices": [
        "World War II"
      ]
    }
  },
  {
    "theme": "AMERICAN HISTORY",
    "section": "Recent American History and Other Important Historical Information",
    "question": "During the Cold War, what was the main concern of the United States?",
    "questionNumber": 83,
    "expectedAnswers": 1,
    "answers": {
      "_type": "text",
      "choices": [
        "Communism"
      ]
    }
  },
  {
    "theme": "AMERICAN HISTORY",
    "section": "Recent American History and Other Important Historical Information",
    "question": "What movement tried to end racial discrimination?",
    "questionNumber": 84,
    "expectedAnswers": 1,
    "answers": {
      "_type": "text",
      "choices": [
        "civil rights (movement)"
      ]
    }
  },
  {
    "theme": "AMERICAN HISTORY",
    "section": "Recent American History and Other Important Historical Information",
    "question": "What did Martin Luther King, Jr. do?*",
    "questionNumber": 85,
    "expectedAnswers": 1,
    "answers": {
      "_type": "text",
      "choices": [
        "fought for civil rights",
        "worked for equality for all Americans"
      ]
    }
  },
  {
    "theme": "AMERICAN HISTORY",
    "section": "Recent American History and Other Important Historical Information",
    "question": "What major event happened on September 11, 2001, in the United States?",
    "questionNumber": 86,
    "expectedAnswers": 1,
    "answers": {
      "_type": "text",
      "choices": [
        "Terrorists attacked the United States."
      ]
    }
  },
  {
    "theme": "AMERICAN HISTORY",
    "section": "Recent American History and Other Important Historical Information",
    "question": "Name one American Indian tribe in the United States.",
    "questionNumber": 87,
    "expectedAnswers": 1,
    "answers": {
      "_type": "text",
      "choices": [
        "Cherokee",
        "Navajo",
        "Sioux",
        "Chippewa",
        "Choctaw",
        "Pueblo",
        "Apache",
        "Iroquois",
        "Creek",
        "Blackfeet",
        "Seminole",
        "Cheyenne",
        "Arawak",
        "Shawnee",
        "Mohegan",
        "Huron",
        "Oneida",
        "Lakota",
        "Crow",
        "Teton",
        "Hopi",
        "Inuit"
      ]
    }
  },
  {
    "theme": "INTEGRATED CIVICS",
    "section": "Geography",
    "question": "Name one of the two longest rivers in the United States.",
    "questionNumber": 88,
    "expectedAnswers": 1,
    "answers": {
      "_type": "text",
      "choices": [
        "Missouri (River)",
        "Mississippi (River)"
      ]
    }
  },
  {
    "theme": "INTEGRATED CIVICS",
    "section": "Geography",
    "question": "What ocean is on the West Coast of the United States?",
    "questionNumber": 89,
    "expectedAnswers": 1,
    "answers": {
      "_type": "text",
      "choices": [
        "Pacific (Ocean)"
      ]
    }
  },
  {
    "theme": "INTEGRATED CIVICS",
    "section": "Geography",
    "question": "What ocean is on the East Coast of the United States?",
    "questionNumber": 90,
    "expectedAnswers": 1,
    "answers": {
      "_type": "text",
      "choices": [
        "Atlantic (Ocean)"
      ]
    }
  },
  {
    "theme": "INTEGRATED CIVICS",
    "section": "Geography",
    "question": "Name one U.S. territory.",
    "questionNumber": 91,
    "expectedAnswers": 1,
    "answers": {
      "_type": "text",
      "choices": [
        "Puerto Rico",
        "U.S. Virgin Islands",
        "American Samoa",
        "Northern Mariana Islands",
        "Guam"
      ]
    }
  },
  {
    "theme": "INTEGRATED CIVICS",
    "section": "Geography",
    "question": "Name one state that borders Canada.",
    "questionNumber": 92,
    "expectedAnswers": 1,
    "answers": {
      "_type": "text",
      "choices": [
        "Maine",
        "New Hampshire",
        "Vermont",
        "New York",
        "Pennsylvania",
        "Ohio",
        "Michigan",
        "Minnesota",
        "North Dakota",
        "Montana",
        "Idaho",
        "Washington",
        "Alaska"
      ]
    }
  },
  {
    "theme": "INTEGRATED CIVICS",
    "section": "Geography",
    "question": "Name one state that borders Mexico.",
    "questionNumber": 93,
    "expectedAnswers": 1,
    "answers": {
      "_type": "text",
      "choices": [
        "California",
        "Arizona",
        "New Mexico",
        "Texas"
      ]
    }
  },
  {
    "theme": "INTEGRATED CIVICS",
    "section": "Geography",
    "question": "What is the capital of the United States?*",
    "questionNumber": 94,
    "expectedAnswers": 1,
    "answers": {
      "_type": "text",
      "choices": [
        "Washington, D.C."
      ]
    }
  },
  {
    "theme": "INTEGRATED CIVICS",
    "section": "Geography",
    "question": "Where is the Statue of Liberty?*",
    "questionNumber": 95,
    "expectedAnswers": 1,
    "answers": {
      "_type": "text",
      "choices": [
        "New York (Harbor)",
        "Liberty Island"
      ]
    }
  },
  {
    "theme": "INTEGRATED CIVICS",
    "section": "Symbols",
    "question": "Why does the flag have 13 stripes?",
    "questionNumber": 96,
    "expectedAnswers": 1,
    "answers": {
      "_type": "text",
      "choices": [
        "because there were 13 original colonies",
        "because the stripes represent the original colonies"
      ]
    }
  },
  {
    "theme": "INTEGRATED CIVICS",
    "section": "Symbols",
    "question": "Why does the flag have 50 stars?*",
    "questionNumber": 97,
    "expectedAnswers": 1,
    "answers": {
      "_type": "text",
      "choices": [
        "because there is one star for each state",
        "because each star represents a state",
        "because there are 50 states"
      ]
    }
  },
  {
    "theme": "INTEGRATED CIVICS",
    "section": "Symbols",
    "question": "What is the name of the national anthem?",
    "questionNumber": 98,
    "expectedAnswers": 1,
    "answers": {
      "_type": "text",
      "choices": [
        "The Star-Spangled Banner"
      ]
    }
  },
  {
    "theme": "INTEGRATED CIVICS",
    "section": "Holidays",
    "question": "When do we celebrate Independence Day?*",
    "questionNumber": 99,
    "expectedAnswers": 1,
    "answers": {
      "_type": "text",
      "choices": [
        "July 4"
      ]
    }
  },
  {
    "theme": "INTEGRATED CIVICS",
    "section": "Holidays",
    "question": "Name two national U.S. holidays.",
    "questionNumber": 100,
    "expectedAnswers": 2,
    "answers": {
      "_type": "text",
      "choices": [
        "New Year’s Day",
        "Martin Luther King, Jr. Day",
        "Presidents’ Day",
        "Memorial Day",
        "Juneteenth",
        "Independence Day",
        "Labor Day",
        "Columbus Day",
        "Veterans Day",
        "Thanksgiving",
        "Christmas"
      ]
    }
  }
]