{
  "1": [
    "Direct democracy",
    "Constitutional monarchy",
    "Parliamentary democracy",
    "Confederation",
    "Oligarchy",
    "Communist state",
    "Theocracy",
    "Socialist republic",
    "Military dictatorship",
    "Absolute monarchy",
    "Authoritarian regime",
    "Unitary state",
    "Aristocracy",
    "Plutocracy",
    "Totalitarian state"
  ],
  "2": [
    "The Declaration of Independence",
    "The Bill of Rights",
    "The Articles of Confederation",
    "The Federalist Papers",
    "The Magna Carta",
    "Federal law",
    "State constitutions",
    "Supreme Court rulings",
    "Executive orders",
    "Congressional statutes",
    "The Emancipation Proclamation",
    "The Treaty of Paris",
    "Common law",
    "The Mayflower Compact",
    "International treaties"
  ],
  "3": [
    "Declares war on foreign nations",
    "Sets tax rates for citizens",
    "Establishes trade agreements",
    "Creates the national currency",
    "Appoints judges directly",
    "Determines election dates",
    "Regulates interstate commerce directly",
    "Sets the national budget",
    "Elects the President",
    "Creates political parties",
    "Mandates military service",
    "Establishes public schools",
    "Sets minimum wage",
    "Creates the postal system",
    "Determines voting age"
  ],
  "4": [
    "Only citizens have rights",
    "The government rules the people",
    "Congress represents everyone",
    "The President speaks for all",
    "All people are taxpayers",
    "Majority rules absolutely",
    "Direct voting on all laws",
    "States have supreme power",
    "The military protects citizens",
    "Property owners make decisions",
    "Religious leaders guide government",
    "Wealthy citizens control policy",
    "Elected officials know best",
    "Courts interpret the will of the people",
    "Federal law overrides individual choice"
  ],
  "5": [
    "Presidential executive orders",
    "Supreme Court decisions",
    "Congressional legislation",
    "Popular vote",
    "State governor agreements",
    "Constitutional conventions only",
    "Federal court rulings",
    "Cabinet recommendations",
    "Public referendums",
    "Senate majority vote alone",
    "House resolution",
    "Treaty ratification",
    "Military approval",
    "State legislature petition",
    "Judicial review"
  ],
  "6": [
    "The powers of Congress",
    "State sovereignty",
    "Presidential authority",
    "Federal court jurisdiction",
    "Military operations",
    "Tax collection procedures",
    "Trade regulations",
    "Immigration policies",
    "Electoral processes",
    "Government budgets",
    "International treaties",
    "Property of corporations",
    "Voting machines",
    "National monuments",
    "Government buildings"
  ],
  "7": [
    "Ten (10)",
    "Fifteen (15)",
    "Twenty (20)",
    "Twenty-five (25)",
    "Twenty-six (26)",
    "Twenty-eight (28)",
    "Thirty (30)",
    "Thirty-three (33)",
    "Fifty (50)",
    "Twelve (12)",
    "Eighteen (18)",
    "Twenty-one (21)",
    "Twenty-two (22)",
    "Twenty-three (23)",
    "Twenty-four (24)"
  ],
  "8": [
    "It created the Constitution",
    "It established the Congress",
    "It outlined the federal budget",
    "It set up the court system",
    "It defined voting procedures",
    "It created the military",
    "It established the presidency",
    "It formed the states",
    "It set tax policies",
    "It created the Bill of Rights",
    "It ended slavery",
    "It gave women the right to vote",
    "It established religious freedom laws",
    "It created the national anthem",
    "It set the national borders"
  ],
  "9": [
    "The Constitution",
    "The Bill of Rights",
    "The Articles of Confederation",
    "The Federalist Papers",
    "The Mayflower Compact",
    "The Treaty of Paris",
    "The Virginia Declaration of Rights",
    "The Magna Carta",
    "The Emancipation Proclamation",
    "The Northwest Ordinance",
    "The Albany Plan",
    "The Continental Charter",
    "The Colonial Proclamation",
    "The Freedom Charter",
    "The Independence Manifesto"
  ],
  "10": [
    "Manifest destiny",
    "Divine right of kings",
    "Absolute monarchy",
    "State supremacy",
    "Military rule",
    "Economic planning",
    "Central banking",
    "Universal healthcare",
    "Public education",
    "Immigration quotas",
    "Trade protectionism",
    "Territorial expansion",
    "National religion",
    "Hereditary leadership",
    "Collective ownership"
  ],
  "11": [
    "The Constitution",
    "The Bill of Rights",
    "The Preamble to the Constitution",
    "The Articles of Confederation",
    "The Federalist Papers",
    "The Mayflower Compact",
    "The Gettysburg Address",
    "The Emancipation Proclamation",
    "The Virginia Declaration of Rights",
    "The First Amendment",
    "The Treaty of Paris",
    "The Northwest Ordinance",
    "The Monroe Doctrine",
    "The Pledge of Allegiance",
    "The National Anthem"
  ],
  "12": [
    "Socialism",
    "Communism",
    "Mixed economy",
    "Command economy",
    "Planned economy",
    "Feudalism",
    "Mercantilism",
    "Barter system",
    "State capitalism",
    "Market socialism",
    "Agrarian economy",
    "Industrial economy",
    "Service economy",
    "Traditional economy",
    "Subsistence economy"
  ],
  "13": [
    "The President makes all laws",
    "Congress controls the courts",
    "Military law applies to civilians",
    "States can ignore federal law",
    "Wealthy citizens are exempt from law",
    "Religious leaders interpret the law",
    "Popular vote overrides law",
    "Executive orders are supreme",
    "Judges create new laws",
    "Police enforce all rules",
    "Citizens vote on every law",
    "Lawyers decide guilt or innocence",
    "The majority is always right",
    "Tradition determines legal outcomes",
    "Custom replaces written law"
  ],
  "14": [
    "The Treaty of Versailles",
    "The Emancipation Proclamation",
    "The Monroe Doctrine",
    "The Gettysburg Address",
    "The Bill of Rights",
    "The Northwest Ordinance",
    "The Louisiana Purchase",
    "The Missouri Compromise",
    "The Stamp Act",
    "The Intolerable Acts",
    "The Quebec Act",
    "The Navigation Acts",
    "The Townshend Acts",
    "The Tea Act",
    "The Proclamation of 1763"
  ],
  "15": [
    "To make government more efficient",
    "To give everyone a voice",
    "To represent different regions",
    "To speed up lawmaking",
    "To reduce government costs",
    "To create more jobs",
    "To honor the founding fathers",
    "To follow British tradition",
    "To represent different classes",
    "To ensure majority rule",
    "To protect minority rights",
    "To simplify the legal system",
    "To manage different types of law",
    "To separate local and federal power",
    "To balance rural and urban interests"
  ],
  "16": [
    "Senate, House, and President",
    "Federal, state, and local",
    "Military, civilian, and judicial",
    "Democratic, Republican, and Independent",
    "Constitutional, statutory, and common",
    "National, regional, and municipal",
    "Administrative, regulatory, and enforcement",
    "Legislative, administrative, and enforcement",
    "Political, economic, and social",
    "Executive, administrative, and judicial",
    "Congress, Cabinet, and courts",
    "President, governors, and mayors",
    "House, Senate, and Cabinet",
    "Supreme, appellate, and district",
    "Federal, appeals, and trial"
  ],
  "17": [
    "Legislative branch",
    "Judicial branch",
    "Congressional branch",
    "Federal branch",
    "Administrative branch",
    "Military branch",
    "National branch",
    "Governmental branch",
    "Constitutional branch",
    "Supreme branch",
    "Senatorial branch",
    "Presidential branch",
    "Regulatory branch",
    "Oversight branch",
    "Central branch"
  ],
  "18": [
    "The President",
    "The Supreme Court",
    "The Executive branch",
    "The Cabinet",
    "Federal agencies",
    "The Senate alone",
    "The House alone",
    "The Vice President",
    "The Attorney General",
    "Federal judges",
    "State governors",
    "The Department of Justice",
    "The White House staff",
    "Constitutional lawyers",
    "The Speaker of the House alone"
  ],
  "19": [
    "Executive and Legislative",
    "Federal and State",
    "Upper and Lower chambers",
    "Democratic and Republican",
    "National and Regional",
    "Majority and Minority",
    "Representatives and Delegates",
    "Senators and Congressmen",
    "Assembly and Council",
    "Parliament and Congress",
    "Legislature and Executive",
    "House and Cabinet",
    "Senate and Cabinet",
    "Congress and Parliament",
    "Chamber and Senate"
  ],
  "20": [
    "Enforces laws",
    "Interprets the Constitution",
    "Commands the military",
    "Appoints Supreme Court justices",
    "Vetoes legislation",
    "Conducts foreign policy",
    "Issues executive orders",
    "Grants pardons",
    "Negotiates treaties alone",
    "Controls state governments",
    "Appoints Cabinet members",
    "Sets interest rates",
    "Prints currency alone",
    "Manages federal agencies",
    "Declares emergencies"
  ],
  "21": [
    "Fifty (50)",
    "Fifty-two (52)",
    "Ninety-eight (98)",
    "One hundred two (102)",
    "One hundred fifty (150)",
    "Two hundred (200)",
    "Four hundred thirty-five (435)",
    "Seventy-five (75)",
    "Eighty (80)",
    "Ninety (90)",
    "One hundred ten (110)",
    "One hundred twenty (120)",
    "Sixty (60)",
    "Forty (40)",
    "Two hundred fifty (250)"
  ],
  "22": [
    "Two (2) years",
    "Four (4) years",
    "Five (5) years",
    "Eight (8) years",
    "Ten (10) years",
    "Three (3) years",
    "One (1) year",
    "Seven (7) years",
    "Life term",
    "Twelve (12) years",
    "Nine (9) years",
    "Unlimited terms",
    "Until retirement",
    "Two terms maximum",
    "No set term"
  ],
  "23": [
    "John Smith",
    "Jane Doe",
    "Robert Wilson",
    "Patricia Johnson",
    "Michael Brown",
    "Elizabeth Davis",
    "William Miller",
    "Jennifer Moore",
    "James Taylor",
    "Mary Anderson",
    "Richard Thomas",
    "Barbara Jackson",
    "Charles White",
    "Susan Harris",
    "Joseph Martin"
  ],
  "24": [
    "One hundred (100)",
    "Two hundred (200)",
    "Three hundred (300)",
    "Four hundred (400)",
    "Four hundred fifty (450)",
    "Five hundred (500)",
    "Five hundred thirty-five (535)",
    "Three hundred fifty (350)",
    "Four hundred twenty-five (425)",
    "Four hundred forty (440)",
    "Four hundred thirty (430)",
    "Four hundred thirty-three (433)",
    "Four hundred thirty-eight (438)",
    "Four hundred forty-five (445)",
    "Three hundred ninety (390)"
  ],
  "25": [
    "One (1) year",
    "Three (3) years",
    "Four (4) years",
    "Five (5) years",
    "Six (6) years",
    "Eight (8) years",
    "Ten (10) years",
    "Life term",
    "Eighteen (18) months",
    "Until reelection",
    "No set term",
    "Seven (7) years",
    "Unlimited",
    "Until resignation",
    "Nine (9) years"
  ],
  "26": [
    "To save government money",
    "To reduce corruption",
    "Because there are more of them",
    "To allow more people to serve",
    "To keep government efficient",
    "Because the House is less important",
    "To balance power with the Senate",
    "Because they represent smaller areas",
    "To limit career politicians",
    "Because the Constitution requires it",
    "To encourage new ideas",
    "To prevent too much power",
    "Because voters prefer shorter terms",
    "To simplify elections",
    "To match state legislatures"
  ],
  "27": [
    "One (1)",
    "Three (3)",
    "Four (4)",
    "Five (5)",
    "Six (6)",
    "Based on population",
    "Varies by state",
    "Ten (10)",
    "Eight (8)",
    "Depends on state size",
    "At least one",
    "No fixed number",
    "Seven (7)",
    "Twelve (12)",
    "Proportional to size"
  ],
  "28": [
    "Based on the original 13 colonies",
    "To balance the House",
    "Because of tradition",
    "To simplify voting",
    "For efficiency",
    "Based on state size",
    "To represent both parties",
    "Because of population",
    "To match the Vice President",
    "For better debate",
    "To prevent ties",
    "Because states requested it",
    "To honor the founders",
    "For geographical balance",
    "To ensure majority rule"
  ],
  "29": [
    "John Smith",
    "Jane Doe",
    "Robert Wilson",
    "Patricia Johnson",
    "Michael Brown",
    "Elizabeth Davis",
    "William Miller",
    "Jennifer Moore",
    "James Taylor",
    "Mary Anderson",
    "Richard Thomas",
    "Barbara Jackson",
    "Charles White",
    "Susan Harris",
    "Joseph Martin"
  ],
  "30": [
    "Nancy Pelosi",
    "Kevin McCarthy",
    "Paul Ryan",
    "John Boehner",
    "Newt Gingrich",
    "Dennis Hastert",
    "Tip O'Neill",
    "Sam Rayburn",
    "Jim Jordan",
    "Hakeem Jeffries",
    "Steve Scalise",
    "Steny Hoyer",
    "Chuck Schumer",
    "Mitch McConnell",
    "Patrick McHenry"
  ],
  "31": [
    "Appointed by the President",
    "Chosen by the Senate",
    "Elected by the people",
    "Selected by the Vice President",
    "Appointed by the Chief Justice",
    "Chosen by the majority party leader",
    "Selected by state governors",
    "Elected by Congress",
    "Appointed by the Cabinet",
    "Chosen by seniority",
    "Selected by the outgoing Speaker",
    "Elected by the Electoral College",
    "Appointed by the President Pro Tempore",
    "Chosen by random selection",
    "Selected by the party convention"
  ],
  "32": [
    "Their congressional district",
    "Only voters in their state",
    "The entire nation",
    "Their political party",
    "Only taxpayers",
    "Property owners in their state",
    "The federal government",
    "Their state legislature",
    "Only registered voters",
    "The President",
    "Their campaign donors",
    "Only citizens who voted for them",
    "The majority party",
    "State government officials",
    "Their home county"
  ],
  "33": [
    "The state legislature",
    "The Electoral College",
    "Congress",
    "The President",
    "State governors",
    "Political parties",
    "The House of Representatives",
    "The Senate itself",
    "Federal judges",
    "County officials",
    "The Cabinet",
    "State courts",
    "The Vice President",
    "The previous senator",
    "A special committee"
  ],
  "34": [
    "The entire state",
    "Only voters",
    "The whole nation",
    "Their political party only",
    "Only taxpayers",
    "The federal government",
    "Only registered voters",
    "The President",
    "Only citizens who voted for them",
    "Their city or town",
    "State government",
    "The majority party",
    "Only homeowners",
    "The Senate",
    "Campaign contributors"
  ],
  "35": [
    "Writes new laws",
    "Enforces existing laws",
    "Vetoes legislation",
    "Declares war",
    "Makes the federal budget",
    "Appoints federal officials",
    "Collects taxes",
    "Commands the military",
    "Conducts foreign policy",
    "Issues executive orders",
    "Manages federal agencies",
    "Prints currency",
    "Regulates commerce",
    "Approves treaties",
    "Sets immigration policy"
  ],
  "36": [
    "Federal Appeals Court",
    "District Court",
    "Court of Appeals",
    "Constitutional Court",
    "High Court",
    "National Court",
    "Federal Court",
    "Superior Court",
    "Circuit Court",
    "Appellate Court",
    "Court of Final Appeals",
    "United States Court of Justice",
    "American High Court",
    "Federal Supreme Court",
    "National Appeals Court"
  ],
  "37": [
    "Five (5)",
    "Six (6)",
    "Seven (7)",
    "Eight (8)",
    "Ten (10)",
    "Eleven (11)",
    "Twelve (12)",
    "Thirteen (13)",
    "Fifteen (15)",
    "Three (3)",
    "Four (4)",
    "Varies by Congress",
    "No fixed number",
    "Determined by the President",
    "Set by the Constitution at twelve"
  ],
  "38": [
    "Six (6) years",
    "Ten (10) years",
    "Fifteen (15) years",
    "Twenty (20) years",
    "Until age 70",
    "Until age 75",
    "Until age 80",
    "Two terms",
    "Four (4) years",
    "Eight (8) years",
    "Twelve (12) years",
    "Until retirement at 65",
    "Twenty-five (25) years",
    "Appointed each presidency",
    "Until reconfirmation"
  ],
  "39": [
    "Samuel Alito",
    "Clarence Thomas",
    "Sonia Sotomayor",
    "Elena Kagan",
    "Neil Gorsuch",
    "Brett Kavanaugh",
    "Amy Coney Barrett",
    "Ketanji Brown Jackson",
    "Ruth Bader Ginsburg",
    "Antonin Scalia",
    "Anthony Kennedy",
    "William Rehnquist",
    "Warren Burger",
    "Earl Warren",
    "John Marshall"
  ],
  "40": [
    "Collect property taxes",
    "Issue marriage licenses",
    "Run public schools",
    "Establish local police",
    "Build state highways",
    "Issue driver's licenses",
    "Regulate local businesses",
    "Set speed limits",
    "Zone land use",
    "License professionals",
    "Manage state parks",
    "Run state prisons",
    "Set drinking age",
    "Issue birth certificates",
    "Conduct local elections"
  ],
  "41": [
    "Print money",
    "Declare war",
    "Make treaties",
    "Regulate immigration",
    "Establish post offices",
    "Coin currency",
    "Conduct foreign relations",
    "Regulate interstate commerce",
    "Maintain the military",
    "Grant patents",
    "Regulate bankruptcy",
    "Establish federal courts",
    "Levy tariffs",
    "Naturalize citizens",
    "Regulate international trade"
  ],
  "42": [
    "It protects freedom of speech",
    "It guarantees the right to bear arms",
    "It prevents unreasonable searches",
    "It ensures a fair trial",
    "It abolishes slavery",
    "It gives women the right to vote",
    "It establishes the income tax",
    "It sets the presidential term limit",
    "It prohibits cruel punishment",
    "It protects religious freedom",
    "It ensures due process",
    "It provides for jury trials",
    "It limits quartering of soldiers",
    "It establishes citizenship rights",
    "It lowers the voting age"
  ],
  "43": [
    "The Vice President",
    "The Speaker of the House",
    "The Senate Majority Leader",
    "The Chief Justice",
    "The Secretary of State",
    "Congress",
    "The Attorney General",
    "The House Majority Leader",
    "The President Pro Tempore",
    "The Cabinet",
    "Federal judges",
    "State governors",
    "The Clerk of the House",
    "The Sergeant at Arms",
    "The Congressional Leadership"
  ],
  "44": [
    "Congress",
    "The Supreme Court",
    "The Vice President",
    "The Speaker of the House",
    "The Senate",
    "The House of Representatives",
    "The Attorney General",
    "The Secretary of State",
    "The Chief Justice",
    "State governors",
    "The Cabinet",
    "Federal judges",
    "The Senate Majority Leader",
    "The President Pro Tempore",
    "The House Majority Leader"
  ],
  "45": [
    "Writes laws for the President",
    "Votes on legislation",
    "Runs the military",
    "Approves Supreme Court justices",
    "Sets tax rates",
    "Creates the federal budget",
    "Declares war",
    "Negotiates treaties alone",
    "Impeaches officials",
    "Interprets the Constitution",
    "Elects the Vice President",
    "Appoints federal judges",
    "Overrides presidential vetoes",
    "Confirms appointments",
    "Manages the courts"
  ],
  "46": [
    "Secretary of Congress",
    "Secretary of the Supreme Court",
    "Secretary of Elections",
    "Secretary of Foreign Affairs",
    "Secretary of the Military",
    "Secretary of Immigration",
    "Secretary of Taxation",
    "Secretary of Justice",
    "Secretary of Industry",
    "Secretary of Public Safety",
    "Secretary of Natural Resources",
    "Secretary of Technology",
    "Secretary of Communications",
    "Secretary of Infrastructure",
    "Secretary of Science"
  ],
  "47": [
    "Writes laws",
    "Votes on legislation",
    "Approves Supreme Court justices",
    "Commands the military directly",
    "Sets tax policy",
    "Creates the federal budget alone",
    "Declares war",
    "Ratifies treaties",
    "Impeaches the President",
    "Interprets laws",
    "Elects the Vice President",
    "Confirms judicial appointments",
    "Overrides vetoes",
    "Manages Congress",
    "Controls federal courts"
  ],
  "48": [
    "Writes laws",
    "Interprets the Constitution",
    "Appoints members of Congress",
    "Declares laws unconstitutional",
    "Sets tax rates",
    "Creates new states",
    "Removes Supreme Court justices",
    "Controls Congress",
    "Prints money",
    "Ratifies amendments",
    "Creates federal courts",
    "Impeaches officials",
    "Sets interest rates",
    "Declares war alone",
    "Approves state laws"
  ],
  "49": [
    "Joe Biden",
    "Barack Obama",
    "George W. Bush",
    "Bill Clinton",
    "George H.W. Bush",
    "Ronald Reagan",
    "Jimmy Carter",
    "Gerald Ford",
    "Richard Nixon",
    "Lyndon Johnson",
    "John F. Kennedy",
    "Dwight Eisenhower",
    "Harry Truman",
    "Franklin Roosevelt",
    "Herbert Hoover"
  ],
  "50": [
    "Kamala Harris",
    "Mike Pence",
    "Joe Biden",
    "Tim Kaine",
    "Paul Ryan",
    "Dick Cheney",
    "Al Gore",
    "Dan Quayle",
    "George H.W. Bush",
    "Walter Mondale",
    "Nelson Rockefeller",
    "Gerald Ford",
    "Spiro Agnew",
    "Hubert Humphrey",
    "Lyndon Johnson"
  ],
  "51": [
    "The Speaker of the House",
    "The President Pro Tempore",
    "The Secretary of State",
    "The Chief Justice",
    "The Senate Majority Leader",
    "The Secretary of Defense",
    "The Attorney General",
    "The Secretary of the Treasury",
    "The House Majority Leader",
    "The First Lady",
    "The previous President",
    "Congress chooses",
    "A special election is held",
    "The Cabinet votes",
    "The Supreme Court decides"
  ],
  "52": [
    "The President Pro Tempore",
    "The Secretary of State",
    "The Chief Justice",
    "The Senate Majority Leader",
    "The Secretary of Defense",
    "The Attorney General",
    "The Secretary of the Treasury",
    "The House Majority Leader",
    "A special election is held",
    "Congress votes",
    "The Cabinet chooses",
    "The Supreme Court decides",
    "The oldest Cabinet member",
    "The former President",
    "The Secretary of Homeland Security"
  ],
  "53": [
    "The Secretary of Defense",
    "The Chairman of the Joint Chiefs",
    "The Vice President",
    "Congress",
    "The Senate",
    "The Secretary of the Army",
    "The Chief of Staff",
    "The National Security Advisor",
    "The Director of the CIA",
    "The Attorney General",
    "A five-star general",
    "The Secretary of State",
    "The highest-ranking general",
    "The Pentagon",
    "The Defense Department"
  ],
  "54": [
    "Twenty-one (21) or older",
    "Twenty-five (25) or older",
    "Thirty (30) or older",
    "Forty (40) or older",
    "Forty-five (45) or older",
    "Fifty (50) or older",
    "Eighteen (18) or older",
    "No age requirement",
    "Thirty-two (32) or older",
    "Thirty-three (33) or older",
    "Thirty-four (34) or older",
    "Thirty-six (36) or older",
    "Thirty-seven (37) or older",
    "Thirty-eight (38) or older",
    "At least retirement age"
  ],
  "55": [
    "In any country",
    "In North America",
    "On U.S. soil only",
    "In the continental U.S.",
    "In one of the original 13 states",
    "In Washington D.C.",
    "In a U.S. state only",
    "In a U.S. territory",
    "On an American military base",
    "Anywhere if parents are citizens",
    "In the Western Hemisphere",
    "In the Americas",
    "In an English-speaking country",
    "In a democracy",
    "In a NATO country"
  ],
  "56": [
    "Pay taxes",
    "Obey the law",
    "Support and defend the Constitution",
    "Serve in the military",
    "Attend school",
    "Work for the government",
    "Own property",
    "Learn English",
    "Register for Selective Service",
    "Carry identification",
    "Report crimes",
    "Respect others' rights",
    "Participate in democracy",
    "Help the community",
    "Know the laws"
  ],
  "57": [
    "Freedom of speech",
    "Freedom of religion",
    "Right to a fair trial",
    "Right to bear arms",
    "Right to own property",
    "Right to work",
    "Right to education",
    "Right to healthcare",
    "Right to privacy",
    "Right to assemble",
    "Right to petition",
    "Right to travel",
    "Right to marry",
    "Right to legal representation",
    "Right to a speedy trial"
  ],
  "58": [
    "The President",
    "The Constitution",
    "The government",
    "Congress",
    "The military",
    "Our state",
    "The Supreme Court",
    "The founding fathers",
    "The Declaration of Independence",
    "The American people",
    "Democracy",
    "Freedom",
    "The republic",
    "Liberty",
    "Our political party"
  ],
  "59": [
    "Learn American history",
    "Speak only English",
    "Vote in every election",
    "Pay extra taxes",
    "Join a political party",
    "Attend civic meetings",
    "Never leave the country",
    "Report to authorities regularly",
    "Work for the government",
    "Teach others about America",
    "Never criticize the government",
    "Support the President",
    "Donate to charity",
    "Serve on every jury",
    "Attend naturalization ceremonies"
  ],
  "60": [
    "Franklin Roosevelt",
    "Theodore Roosevelt",
    "William Howard Taft",
    "Warren Harding",
    "Calvin Coolidge",
    "Herbert Hoover",
    "Dwight Eisenhower",
    "Harry Truman",
    "William McKinley",
    "Grover Cleveland",
    "Benjamin Harrison",
    "Chester Arthur",
    "James Garfield",
    "Rutherford Hayes",
    "Ulysses Grant"
  ],
  "61": [
    "John Smith",
    "Jane Doe",
    "Robert Wilson",
    "Patricia Johnson",
    "Michael Brown",
    "Elizabeth Davis",
    "William Miller",
    "Jennifer Moore",
    "James Taylor",
    "Mary Anderson",
    "Richard Thomas",
    "Barbara Jackson",
    "Charles White",
    "Susan Harris",
    "Joseph Martin"
  ],
  "62": [
    "Springfield",
    "Madison",
    "Franklin",
    "Washington",
    "Jefferson",
    "Lincoln",
    "Columbus",
    "Jackson",
    "Cleveland",
    "Portland",
    "Burlington",
    "Georgetown",
    "Charleston",
    "Alexandria",
    "Richmond"
  ],
  "63": [
    "Only property owners can vote",
    "Citizens must pass a literacy test",
    "Only citizens over 21 can vote",
    "Voting is mandatory for all citizens",
    "Only college graduates can vote",
    "Citizens must register 90 days early",
    "Only English speakers can vote",
    "Voting requires a photo ID",
    "Only employed citizens can vote",
    "Citizens must vote in person",
    "Only native-born citizens can vote",
    "Voting requires military service",
    "Only married citizens can vote",
    "Citizens must own land to vote",
    "Only taxpayers can vote"
  ],
  "64": [
    "Legal residents",
    "Green card holders",
    "Permanent residents",
    "Anyone over 18",
    "All adults",
    "Taxpayers",
    "Property owners",
    "Registered voters",
    "Native-born Americans",
    "Military personnel",
    "Government employees",
    "Naturalized immigrants",
    "Legal immigrants",
    "Workers with visas",
    "Long-term residents"
  ],
  "65": [
    "Right to vote in federal elections",
    "Right to run for President",
    "Right to serve on federal juries",
    "Right to a U.S. passport",
    "Right to free healthcare",
    "Right to free education",
    "Right to government housing",
    "Right to a job",
    "Right to welfare",
    "Right to free legal representation",
    "Right to unemployment benefits",
    "Right to Social Security",
    "Right to Medicare",
    "Right to food stamps",
    "Right to free transportation"
  ],
  "66": [
    "Bear arms",
    "Fair trial",
    "No cruel punishment",
    "Privacy",
    "Vote",
    "Own property",
    "Travel freely",
    "Speedy trial",
    "Jury trial",
    "No double jeopardy",
    "No self-incrimination",
    "Due process",
    "Equal protection",
    "No unreasonable searches",
    "Counsel in court"
  ],
  "67": [
    "Five (5)",
    "Seven (7)",
    "Eight (8)",
    "Nine (9)",
    "Eleven (11)",
    "Twelve (12)",
    "Thirteen (13)",
    "Fifteen (15)",
    "Twenty (20)",
    "Twenty-seven (27)",
    "Six (6)",
    "Three (3)",
    "Four (4)",
    "Fourteen (14)",
    "Sixteen (16)"
  ],
  "68": [
    "Ended the Civil War",
    "Gave women the right to vote",
    "Abolished slavery everywhere",
    "Created the 13th Amendment",
    "Freed all slaves immediately",
    "Ended segregation",
    "Gave citizenship to former slaves",
    "Allowed Black men to vote",
    "Integrated the military",
    "Ended indentured servitude",
    "Created civil rights",
    "Established equal rights",
    "Ended the slave trade",
    "Prohibited discrimination",
    "Granted land to freed slaves"
  ],
  "69": [
    "Abolished slavery",
    "Gave citizenship to all born in U.S.",
    "Allowed all men to vote",
    "Prohibited poll taxes",
    "Lowered voting age to 18",
    "Established Prohibition",
    "Ended Prohibition",
    "Created the income tax",
    "Limited presidential terms",
    "Gave D.C. electoral votes",
    "Established direct election of senators",
    "Granted civil rights",
    "Ended segregation",
    "Established equal pay",
    "Prohibited gender discrimination"
  ],
  "70": [
    "Wrote the Constitution",
    "Founded the Red Cross",
    "Led the Underground Railroad",
    "Served as First Lady",
    "Became the first female senator",
    "Started the civil rights movement",
    "Founded the NAACP",
    "Wrote the Bill of Rights",
    "Served in Congress",
    "Became a Supreme Court justice",
    "Led the abolitionist movement",
    "Founded the labor movement",
    "Became the first female governor",
    "Started public education",
    "Founded women's colleges"
  ],
  "71": [
    "Revolutionary War",
    "World War I",
    "World War II",
    "Korean War",
    "Vietnam War",
    "French and Indian War",
    "Persian Gulf War",
    "War in Afghanistan",
    "War in Iraq",
    "Quasi-War",
    "Barbary Wars",
    "Indian Wars",
    "Philippine-American War",
    "Boxer Rebellion",
    "Seven Years War"
  ],
  "72": [
    "Revolutionary War",
    "War of 1812",
    "Mexican-American War",
    "Spanish-American War",
    "World War I",
    "The Great War",
    "The American Revolution",
    "The War of Independence",
    "The Confederate War",
    "The Secession War",
    "The Union War",
    "The Rebellion",
    "The Brothers' War",
    "The States' War",
    "The Federal War"
  ],
  "73": [
    "Taxation without representation",
    "British occupation",
    "Mexican border disputes",
    "Native American conflicts",
    "French interference",
    "Religious persecution",
    "Trade embargoes",
    "Immigration policies",
    "Currency disputes",
    "Maritime rights",
    "Colonial expansion",
    "Presidential election fraud",
    "Congressional corruption",
    "Foreign alliances",
    "Military draft"
  ],
  "74": [
    "Wrote the Constitution",
    "Founded the Republican Party",
    "Defeated the British",
    "Purchased Louisiana",
    "Built the transcontinental railroad",
    "Founded public schools",
    "Created the income tax",
    "Established the Supreme Court",
    "Wrote the Bill of Rights",
    "Ended Reconstruction",
    "Started the Civil War",
    "Invaded Mexico",
    "Negotiated with Britain",
    "Founded the army",
    "Created the postal service"
  ],
  "75": [
    "Ended the Civil War",
    "Gave women the right to vote",
    "Abolished slavery everywhere",
    "Created the 13th Amendment",
    "Freed all slaves immediately",
    "Ended segregation",
    "Gave citizenship to former slaves",
    "Allowed Black men to vote",
    "Integrated the military",
    "Ended indentured servitude",
    "Created civil rights",
    "Established equal rights",
    "Ended the slave trade",
    "Prohibited discrimination",
    "Granted land to freed slaves"
  ],
  "76": [
    "Revolutionary War",
    "War of 1812",
    "Mexican-American War",
    "Spanish-American War",
    "World War I",
    "World War II",
    "Korean War",
    "Vietnam War",
    "French and Indian War",
    "The Great War",
    "The War of Independence",
    "The Reconstruction War",
    "The Abolition War",
    "The Emancipation War",
    "The Freedom War"
  ],
  "77": [
    "14th Amendment",
    "15th Amendment",
    "1st Amendment",
    "5th Amendment",
    "10th Amendment",
    "12th Amendment",
    "16th Amendment",
    "19th Amendment",
    "Bill of Rights",
    "Emancipation Proclamation",
    "11th Amendment",
    "18th Amendment",
    "21st Amendment",
    "26th Amendment",
    "The original Constitution"
  ],
  "78": [
    "Franklin Roosevelt",
    "Theodore Roosevelt",
    "William Howard Taft",
    "Warren Harding",
    "Calvin Coolidge",
    "Herbert Hoover",
    "Dwight Eisenhower",
    "Harry Truman",
    "William McKinley",
    "Grover Cleveland",
    "Benjamin Harrison",
    "Chester Arthur",
    "James Garfield",
    "Rutherford Hayes",
    "Ulysses Grant"
  ],
  "79": [
    "13th Amendment",
    "15th Amendment",
    "1st Amendment",
    "5th Amendment",
    "10th Amendment",
    "12th Amendment",
    "16th Amendment",
    "19th Amendment",
    "Bill of Rights",
    "11th Amendment",
    "18th Amendment",
    "21st Amendment",
    "26th Amendment",
    "The original Constitution",
    "4th Amendment"
  ],
  "80": [
    "George Washington",
    "Thomas Jefferson",
    "Benjamin Franklin",
    "John Adams",
    "Samuel Adams",
    "Patrick Henry",
    "Thomas Paine",
    "Paul Revere",
    "John Hancock",
    "George Mason",
    "Roger Sherman",
    "Gouverneur Morris",
    "Robert Morris",
    "Edmund Randolph",
    "William Paterson"
  ],
  "81": [
    "The Constitution",
    "The Bill of Rights",
    "The Articles of Confederation",
    "The Federalist Papers",
    "The Mayflower Compact",
    "The Treaty of Paris",
    "The Virginia Declaration of Rights",
    "The Magna Carta",
    "The Emancipation Proclamation",
    "The Northwest Ordinance",
    "The Albany Plan",
    "The Continental Charter",
    "The Colonial Proclamation",
    "The Freedom Charter",
    "The Independence Manifesto"
  ],
  "82": [
    "First President",
    "Wrote the Constitution alone",
    "Led the Revolutionary Army",
    "Discovered America",
    "Invented the telephone",
    "First Vice President",
    "Founded Harvard University",
    "Wrote the Declaration of Independence alone",
    "Commanded the Navy",
    "Invented the steam engine",
    "Founded the first bank",
    "First Chief Justice",
    "Discovered electricity",
    "Invented the printing press",
    "Founded the first hospital"
  ],
  "83": [
    "Thomas Jefferson",
    "Benjamin Franklin",
    "John Adams",
    "James Madison",
    "Alexander Hamilton",
    "Abraham Lincoln",
    "Theodore Roosevelt",
    "John Hancock",
    "Samuel Adams",
    "Patrick Henry",
    "Thomas Paine",
    "Paul Revere",
    "John Jay",
    "James Monroe",
    "Andrew Jackson"
  ],
  "84": [
    "Wrote the Constitution",
    "Wrote the Declaration of Independence",
    "Invented electricity",
    "Founded the Democratic Party",
    "Abolished slavery",
    "Won the Civil War",
    "Purchased Louisiana",
    "Built the White House",
    "Created the Supreme Court",
    "Founded the first bank",
    "Negotiated the Treaty of Paris alone",
    "Discovered America",
    "First Chief Justice",
    "Wrote the Bill of Rights",
    "Founded public schools"
  ],
  "85": [
    "First President",
    "Led the Continental Army",
    "Wrote the Constitution",
    "Father of the Constitution",
    "First Chief Justice",
    "Founded the Republican Party",
    "Abolished slavery",
    "Won the Civil War",
    "Invented the light bulb",
    "Founded Harvard",
    "First Secretary of Treasury",
    "Wrote the Federalist Papers",
    "Commanded the Navy",
    "Founded the first bank",
    "Built the White House"
  ],
  "86": [
    "July 4, 1775",
    "July 4, 1777",
    "July 4, 1783",
    "July 4, 1787",
    "July 4, 1789",
    "June 4, 1776",
    "August 4, 1776",
    "September 4, 1776",
    "July 1, 1776",
    "July 2, 1776",
    "July 3, 1776",
    "July 5, 1776",
    "December 25, 1776",
    "January 1, 1776",
    "October 4, 1776"
  ],
  "87": [
    "Battle of Gettysburg",
    "Battle of Antietam",
    "Battle of Fort Sumter",
    "Battle of Bull Run",
    "Battle of New Orleans",
    "Trail of Tears",
    "Louisiana Purchase",
    "Constitutional Convention",
    "Emancipation Proclamation",
    "Lewis and Clark Expedition",
    "Battle of the Alamo",
    "Pearl Harbor",
    "D-Day",
    "Battle of Midway",
    "Signing of the Constitution"
  ],
  "88": [
    "Vermont",
    "Maine",
    "Ohio",
    "Kentucky",
    "Tennessee",
    "West Virginia",
    "Florida",
    "Louisiana",
    "Texas",
    "California",
    "Oregon",
    "Washington",
    "Michigan",
    "Illinois",
    "Indiana"
  ],
  "89": [
    "George Washington",
    "Thomas Jefferson",
    "Benjamin Franklin",
    "John Adams",
    "Alexander Hamilton",
    "John Jay",
    "Samuel Adams",
    "Patrick Henry",
    "John Hancock",
    "James Monroe",
    "Gouverneur Morris",
    "Roger Sherman",
    "George Mason",
    "Edmund Randolph",
    "Charles Pinckney"
  ],
  "90": [
    "Florida",
    "Texas",
    "Alaska",
    "California",
    "Oregon Territory",
    "New Mexico",
    "Arizona",
    "Nevada",
    "Utah",
    "Colorado",
    "Kansas",
    "Nebraska",
    "The Northwest Territory",
    "Puerto Rico",
    "Virgin Islands"
  ],
  "91": [
    "Revolutionary War",
    "World War I",
    "World War II",
    "Korean War",
    "Vietnam War",
    "French and Indian War",
    "Persian Gulf War",
    "War in Afghanistan",
    "War in Iraq",
    "Quasi-War",
    "Barbary Wars",
    "Seven Years War",
    "Cold War",
    "War of Independence",
    "Colonial Wars"
  ],
  "92": [
    "Revolutionary War",
    "War of 1812",
    "Mexican-American War",
    "Spanish-American War",
    "World War I",
    "World War II",
    "Korean War",
    "Vietnam War",
    "The Great War",
    "The War of Independence",
    "The Confederate War",
    "The Secession War",
    "The Union War",
    "The Rebellion",
    "The Federal War"
  ],
  "93": [
    "Taxation without representation",
    "British occupation",
    "Mexican border disputes",
    "Native American conflicts",
    "French interference",
    "Religious persecution",
    "Trade embargoes",
    "Immigration policies",
    "Currency disputes",
    "Maritime rights",
    "Colonial expansion",
    "Presidential assassination",
    "Congressional corruption",
    "Foreign alliances",
    "Military draft"
  ],
  "94": [
    "Wrote the Constitution",
    "Founded the Republican Party alone",
    "Defeated the British",
    "Purchased Louisiana",
    "Built the transcontinental railroad",
    "Founded public schools",
    "Created the income tax",
    "Established the Supreme Court",
    "Wrote the Bill of Rights",
    "Ended Reconstruction",
    "Started the Civil War",
    "Invaded Mexico",
    "Negotiated with Britain",
    "Founded the army",
    "Created the postal service"
  ],
  "95": [
    "Ended the Civil War",
    "Gave women the right to vote",
    "Abolished slavery everywhere",
    "Created the 13th Amendment",
    "Freed all slaves immediately",
    "Ended segregation",
    "Gave citizenship to former slaves",
    "Allowed Black men to vote",
    "Integrated the military",
    "Ended indentured servitude",
    "Created civil rights",
    "Established equal rights",
    "Ended the slave trade",
    "Prohibited discrimination",
    "Granted land to freed slaves"
  ],
  "96": [
    "Revolutionary War",
    "War of 1812",
    "Mexican-American War",
    "Spanish-American War",
    "World War I",
    "World War II",
    "Korean War",
    "Vietnam War",
    "French and Indian War",
    "The Great War",
    "The War of Independence",
    "The Reconstruction War",
    "The Abolition War",
    "The Emancipation War",
    "The Freedom War"
  ],
  "97": [
    "13th Amendment",
    "15th Amendment",
    "1st Amendment",
    "5th Amendment",
    "10th Amendment",
    "12th Amendment",
    "16th Amendment",
    "19th Amendment",
    "Bill of Rights",
    "11th Amendment",
    "18th Amendment",
    "21st Amendment",
    "26th Amendment",
    "The original Constitution",
    "4th Amendment"
  ],
  "98": [
    "At the founding of the nation",
    "After the Revolutionary War",
    "In 1787",
    "In 1800",
    "After World War I",
    "In 1920",
    "With the Bill of Rights",
    "In 1776",
    "After the War of 1812",
    "In 1850",
    "With the 14th Amendment",
    "With the 19th Amendment",
    "In 1900",
    "After World War II",
    "With the 26th Amendment"
  ],
  "99": [
    "Clara Barton",
    "Florence Nightingale",
    "Jane Addams",
    "Eleanor Roosevelt",
    "Rosa Parks",
    "Abigail Adams",
    "Dolley Madison",
    "Martha Washington",
    "Betsy Ross",
    "Pocahontas",
    "Sacagawea",
    "Louisa May Alcott",
    "Emily Dickinson",
    "Harriet Beecher Stowe",
    "Mary Todd Lincoln"
  ],
  "100": [
    "Revolutionary War",
    "Civil War",
    "War of 1812",
    "Mexican-American War",
    "Spanish-American War",
    "War in Afghanistan",
    "War in Iraq",
    "French and Indian War",
    "Indian Wars",
    "Cold War",
    "War of Independence",
    "Barbary Wars",
    "Philippine-American War",
    "Boxer Rebellion",
    "Banana Wars"
  ],
  "101": [
    "Japan attacked Pearl Harbor",
    "To stop communism",
    "To liberate Europe from Nazi Germany",
    "Because of the assassination of an American",
    "To protect American territory",
    "Because of a direct attack on U.S. soil",
    "To defend France from invasion",
    "Because of trade disputes",
    "To honor a treaty with Britain",
    "Because of the sinking of the Titanic",
    "To acquire new territory",
    "To spread democracy",
    "Because of the Mexican-American border",
    "To protect oil interests",
    "Because of terrorism"
  ],
  "102": [
    "1870",
    "1900",
    "1910",
    "1930",
    "1940",
    "1950",
    "After the Civil War",
    "With the 15th Amendment",
    "With the 18th Amendment",
    "With the 21st Amendment",
    "After World War II",
    "In the 1800s",
    "At the founding of the nation",
    "1776",
    "1890"
  ],
  "103": [
    "A major war in Europe",
    "A natural disaster",
    "A period of extreme drought",
    "A disease epidemic",
    "A political scandal",
    "A stock market boom",
    "A period of inflation",
    "A technological revolution",
    "A cultural movement",
    "A real estate bubble",
    "A banking holiday",
    "A labor strike",
    "A government shutdown",
    "A famine",
    "A civil unrest period"
  ],
  "104": [
    "1919",
    "1920",
    "1925",
    "1930",
    "1931",
    "1932",
    "1933",
    "1935",
    "1939",
    "1941",
    "World War I",
    "World War II",
    "End of Prohibition",
    "After the New Deal",
    "1927"
  ],
  "105": [
    "Theodore Roosevelt",
    "Woodrow Wilson",
    "Herbert Hoover",
    "Harry Truman",
    "Calvin Coolidge",
    "Warren Harding",
    "Dwight Eisenhower",
    "John F. Kennedy",
    "Lyndon Johnson",
    "Richard Nixon",
    "Gerald Ford",
    "Jimmy Carter",
    "Ronald Reagan",
    "George H.W. Bush",
    "William Taft"
  ],
  "106": [
    "Germany attacked U.S. ships",
    "To stop communism",
    "Because of the assassination of a leader",
    "To acquire new territory",
    "Because of trade disputes",
    "To honor a treaty",
    "Because of the Great Depression",
    "To protect oil interests",
    "Because of terrorism",
    "To spread democracy",
    "Because of border disputes",
    "To defend Britain from invasion",
    "Because of submarine warfare",
    "To protect American investments",
    "Because of the Holocaust"
  ],
  "107": [
    "General during World War I",
    "Led the D-Day invasion of Japan",
    "President during Vietnam War",
    "Founded NASA",
    "Ended the Great Depression",
    "Created Social Security",
    "Wrote the GI Bill",
    "Founded the United Nations",
    "Dropped the atomic bomb",
    "Negotiated the Treaty of Versailles",
    "Founded the Peace Corps",
    "Ended Prohibition",
    "Created Medicare",
    "Won the Civil War",
    "Purchased Alaska"
  ],
  "108": [
    "Germany",
    "Japan",
    "China",
    "North Korea",
    "Cuba",
    "Vietnam",
    "Iran",
    "Iraq",
    "Britain",
    "France",
    "Italy",
    "Spain",
    "Mexico",
    "Canada",
    "India"
  ],
  "109": [
    "Fascism",
    "Terrorism",
    "Immigration",
    "Economic recession",
    "Climate change",
    "Trade deficits",
    "Healthcare",
    "Education",
    "Poverty",
    "Crime",
    "Drug trafficking",
    "Inflation",
    "Unemployment",
    "Environmental pollution",
    "Natural disasters"
  ],
  "110": [
    "Japan attacked the U.S.",
    "Korea attacked the U.S.",
    "To liberate Korea from Japan",
    "Because of oil interests",
    "To protect American territory",
    "Because of a treaty obligation",
    "To spread democracy",
    "Because of terrorism",
    "To acquire new territory",
    "Because of trade disputes",
    "To support United Nations",
    "Because Korea had weapons of mass destruction",
    "To protect human rights",
    "Because of border disputes",
    "To honor an alliance"
  ],
  "111": [
    "Vietnam attacked the U.S.",
    "To liberate Vietnam from France",
    "Because of oil interests",
    "To protect American territory",
    "Because of a treaty obligation",
    "To spread capitalism",
    "Because of terrorism",
    "To acquire new territory",
    "Because of trade disputes",
    "To support the United Nations",
    "Because Vietnam had nuclear weapons",
    "To protect human rights",
    "Because of border disputes",
    "To honor a defense pact",
    "Because of the Gulf of Tonkin lie"
  ],
  "112": [
    "Fought for women's suffrage",
    "Ended the Vietnam War",
    "Established labor unions",
    "Created Social Security",
    "Founded public schools",
    "Established Medicare",
    "Created environmental protections",
    "Founded the United Nations",
    "Ended Prohibition",
    "Established the minimum wage",
    "Created unemployment insurance",
    "Founded the Peace Corps",
    "Established workers' compensation",
    "Created child labor laws",
    "Founded the ACLU"
  ],
  "113": [
    "Founded the NAACP",
    "Was the first Black president",
    "Wrote the Civil Rights Act",
    "Served in Congress",
    "Was a Supreme Court justice",
    "Led the Montgomery boycott alone",
    "Founded Black Lives Matter",
    "Was Vice President",
    "Wrote the Voting Rights Act",
    "Led the Underground Railroad",
    "Founded the Black Panthers",
    "Was a military general",
    "Served in the Senate",
    "Founded the Urban League",
    "Led the Freedom Riders alone"
  ],
  "114": [
    "Iraq attacked the United States",
    "To find weapons of mass destruction",
    "To remove Saddam Hussein",
    "Because of September 11",
    "To protect Israel",
    "To spread democracy",
    "Because of terrorism",
    "To protect Saudi Arabia alone",
    "To control oil production",
    "Because of nuclear threats",
    "To honor a treaty",
    "To defend Iran",
    "Because Iraq invaded Saudi Arabia",
    "To stop communism",
    "Because of border disputes"
  ],
  "115": [
    "The stock market crashed",
    "A hurricane hit New York",
    "The President was assassinated",
    "War was declared on Iraq",
    "An earthquake struck California",
    "The Berlin Wall fell",
    "The Soviet Union collapsed",
    "A nuclear accident occurred",
    "The space shuttle exploded",
    "A major blackout occurred",
    "The Gulf War began",
    "Oklahoma City was bombed",
    "The Twin Towers were built",
    "A tornado hit the Midwest",
    "Congress was attacked"
  ],
  "116": [
    "Vietnam War",
    "Korean War",
    "Persian Gulf War",
    "World War II",
    "Cold War",
    "Bay of Pigs",
    "Grenada invasion",
    "Panama invasion",
    "Kosovo conflict",
    "Bosnia conflict",
    "Libya conflict",
    "Syria conflict",
    "Yemen conflict",
    "Somalia conflict",
    "Sudan conflict"
  ],
  "117": [
    "Aztec",
    "Maya",
    "Inca",
    "Olmec",
    "Toltec",
    "Mayan",
    "Incan",
    "Taino",
    "Arawak",
    "Carib",
    "Mapuche",
    "Guarani",
    "Quechua",
    "Zapotec",
    "Mixtec"
  ],
  "118": [
    "Steam engine",
    "Printing press",
    "Compass",
    "Gunpowder",
    "Paper",
    "Wheel",
    "Telescope",
    "Microscope",
    "Penicillin",
    "Vaccination",
    "Radio",
    "Television",
    "World Wide Web",
    "Nuclear power",
    "Jet engine"
  ],
  "119": [
    "New York City",
    "Los Angeles",
    "Chicago",
    "Philadelphia",
    "Boston",
    "San Francisco",
    "Houston",
    "Dallas",
    "Atlanta",
    "Miami",
    "Seattle",
    "Denver",
    "Phoenix",
    "Detroit",
    "Baltimore"
  ],
  "120": [
    "Washington, D.C.",
    "Boston Harbor",
    "Philadelphia",
    "Baltimore",
    "San Francisco Bay",
    "Los Angeles",
    "Chicago",
    "Miami",
    "Seattle",
    "New Orleans",
    "Ellis Island",
    "Manhattan",
    "Brooklyn",
    "Long Island",
    "Central Park"
  ],
  "121": [
    "For the 13 amendments in the Bill of Rights",
    "For the 13 signers of the Declaration",
    "For the 13 founding fathers",
    "For the 13 original states after the Constitution",
    "For good luck",
    "For the 13 battles of the Revolution",
    "For the 13 months of the year",
    "For the 13 original territories",
    "For the 13 presidents",
    "For the 13 Supreme Court justices",
    "For the 13 cabinet positions",
    "For the 13 congressional districts",
    "For the 13 stars on the original flag",
    "For the 13 original settlements",
    "For aesthetic balance"
  ],
  "122": [
    "For the 50 original colonies",
    "For the 50 signers of the Constitution",
    "For the 50 founding fathers",
    "For the 50 amendments",
    "For the 50 senators",
    "For good luck",
    "For the 50 battles won",
    "For the 50 territories",
    "For aesthetic design",
    "For the 50 governors",
    "For the 50 congressional districts",
    "For the 50 Supreme Court decisions",
    "For the 50 presidents",
    "For the 50 cabinet positions",
    "For the 50 national parks"
  ],
  "123": [
    "America the Beautiful",
    "God Bless America",
    "My Country, 'Tis of Thee",
    "The Battle Hymn of the Republic",
    "Yankee Doodle",
    "Hail to the Chief",
    "This Land Is Your Land",
    "America",
    "The Stars and Stripes Forever",
    "Columbia, the Gem of the Ocean",
    "The Liberty Bell March",
    "The Washington Post March",
    "Born in the USA",
    "Proud to Be an American",
    "The National March"
  ],
  "124": [
    "In God we trust",
    "Liberty and justice for all",
    "Land of the free",
    "One nation under God",
    "United we stand",
    "Freedom for all",
    "Strength through unity",
    "Many states, one nation",
    "Together we prevail",
    "One for all, all for one",
    "Unity in diversity",
    "From sea to shining sea",
    "Don't tread on me",
    "Live free or die",
    "Eternal vigilance"
  ],
  "125": [
    "The day the Constitution was signed",
    "The day the Revolutionary War ended",
    "The day George Washington became President",
    "The day the Bill of Rights was ratified",
    "The day slavery was abolished",
    "The day women got the right to vote",
    "Memorial Day",
    "Veterans Day",
    "Labor Day",
    "Presidents Day",
    "The day Congress first met",
    "The day the flag was created",
    "The day the last British troops left",
    "Thanksgiving",
    "Columbus Day"
  ],
  "126": [
    "Valentine's Day",
    "St. Patrick's Day",
    "Easter",
    "Mother's Day",
    "Father's Day",
    "Halloween",
    "Earth Day",
    "Flag Day",
    "Groundhog Day",
    "April Fools' Day",
    "Cinco de Mayo",
    "Black Friday",
    "Super Bowl Sunday",
    "Election Day",
    "Tax Day"
  ],
  "127": [
    "A holiday to honor all living veterans",
    "A holiday to honor the President",
    "A holiday celebrating the end of World War II",
    "A holiday to remember Pearl Harbor",
    "A holiday to honor police officers",
    "A holiday to honor firefighters",
    "A holiday for all government workers",
    "A holiday to remember September 11",
    "The official start of summer",
    "A holiday to honor the founding fathers",
    "A holiday to celebrate independence",
    "A holiday to honor teachers",
    "A holiday for workers' rights",
    "A holiday to honor civil rights leaders",
    "A holiday celebrating the Constitution"
  ],
  "128": [
    "A holiday to honor soldiers who died",
    "A holiday to celebrate the end of World War I",
    "A holiday to honor the President",
    "A holiday celebrating independence",
    "A holiday to honor police officers",
    "A holiday to honor firefighters",
    "A holiday to remember September 11",
    "A holiday for workers' rights",
    "A holiday to honor government workers",
    "A holiday to remember Pearl Harbor",
    "The official end of summer",
    "A holiday to honor the founding fathers",
    "A holiday to honor teachers",
    "A holiday celebrating the Constitution",
    "A holiday to honor civil rights leaders"
  ]
}
